Workbook

Sheet README
B2: Arsitektur World Model pada Domain Video: Perbandingan Joint Embedding Predictive Architectures (JEPA) dan Generatif
B4: Anggota
B5: M. Hikari Reiziq Rakhmadinta | C5: 5027241079
B6: Arya Bisma Putra Refman | C6: 5027241036
B7: Ahmad Syauqi Reza | C7: 50027241085
B8: M. Fatihul Qolbi Ash Shidiqi | C8: 5027241023
B10: Kitchenham-Style Systematic Literature Review Workbook
B11: Workflow: Raw Article Data → Inclusion/Exclusion Screening → Candidate Papers → Quality Assessment → Final Papers
B12: Purpose | C12: A practical Excel template for conducting a systematic literature review using the main stages described by Kitchenham & Charters: identification, study selection, quality assessment, data extraction, and synthesis.
B13: Important note | C13: Kitchenham does not prescribe one universal numerical inclusion/exclusion score or one universal quality checklist. The scoring rules in this workbook are an operational template that should be adapted to your review protocol and research questions.
B14: PICOC & Search Strategy | C14: Use PICOC_RQs to define Population, Intervention, Comparison, Outcome, and Context and formulate RQs. Use Search_Strategy to document exact database queries, dates, filters, fields, and results. Use Databases to document database selection.
B15: Raw_Articles | C15: Enter every record retrieved from databases/registers and, when applicable, other identification methods such as backward/forward snowballing.
B16: Screening | C16: Apply your predefined inclusion and exclusion criteria. The workbook calculates an inclusion score and identifies candidate papers.
B17: Quality_Assessment | C17: Assess candidate papers using a tailored quality checklist. Default scoring: Yes = 1, Partly = 0.5, No/Unknown = 0.
B18: Final_Papers | C18: Contains papers that pass the quality threshold and are retained for final data extraction.
B19: PRISMA_Counts | C19: Summarizes counts needed to help populate a PRISMA 2020 flow diagram.
B20: Recommended practice | C20: Define inclusion/exclusion criteria and QA thresholds in your protocol before screening. Pilot the criteria on a small sample and revise them if they cannot be applied consistently.
B21: QA scoring | C21: QA uses a 1–3 scale: 1 = Low quality, 2 = Moderate quality, 3 = High quality. With 8 QA questions, maximum score = 24.
B22: QA decision | C22: Default threshold: ≥75% = Final; 60–74.9% = Review; <60% = Exclude. These thresholds are configurable and should be justified in the review protocol.

Sheet PICOC_RQs
B2: PICOC Framework & Research Question Formulation
B3: Use PICOC to translate the research problem into searchable concepts and formulate focused research questions.
B5: Element | C5: Meaning | D5: Your Definition | E5: Notes
B6: P – Population | C6: Who/what is being studied? | D6: Sistem kecerdasan buatan dengan world model untuk simulasi dan prediksi kelanjutan adegan pada lingkungan digital | E6: Model yang memetakan kondisi saat ini ke kondisi masa depan
B7: I – Intervention | C7: Technology, method, treatment, or approach being investigated | D7: Arsitektur berbasis representasi laten non-generatif (JEPA) | E7: I-JEPA, V-JEPA, MC-JEPA, LeWM
B8: C – Comparison | C8: Alternative intervention, baseline, or comparator | D8: Arsitektur world model generatif berbasis piksel/video/diffusion | E8: Video diffusion models, autoregressive, DreamerV3, Ha & Schmidhuber
B9: O – Outcome | C9: What result/effect/performance is being evaluated? | D9: Efisiensi komputasi (FLOPs/memori), efisiensi data/sampel, stabilitas representasi (minim kolaps/halusinasi), dan performa pada tugas hilir (downstream tasks) — dibatasi ke tiga kelompok: (1) video/frame prediction (FVD/PSNR/SSIM), (2) representation probing dengan frozen encoder (action recognition, image/video classification), dan (3) planning/control pada simulasi digital (model-based RL). | E9: Metrik komputasi, akurasi probing, konsistensi representasi
B10: C – Context | C10: Environment/domain in which the study occurs | D10: Pemodelan visual, representasi data video, dan lingkungan simulasi digital | E10: Benchmark video (action-conditioned), gim simulasi murni perangkat lunak
B13: Research Question Formulation
B15: RQ ID | C15: Research Question | D15: PICOC Elements Used
B16: RQ-01 | C16: Apa saja paradigma arsitektural utama pada garis keturunan JEPA dan garis keturunan generatif dalam pemodelan dunia (world modeling), dan bagaimana evolusinya sejak 2018 hingga saat ini? | D16: P, I, C(Comparison)
B17: RQ-02 | C17: Apa perbedaan mendasar dalam fungsi objektif pembelajaran (loss functions) dan strategi representasi antara world model berbasis JEPA (prediksi laten) dan generatif (prediksi piksel)? | D17: I, C(Comparison), O
B18: RQ-03 | C18: Bagaimana perbandingan performa masing-masing garis keturunan pada tugas prediksi sekuens video (video prediction) dan simulasi interaktif pada lingkungan virtual? | D18: I, C(Comparison), O, C(Context)
B19: RQ-04 | C19: Bagaimana trade-off efisiensi komputasi dan efisiensi sampel antara world model berbasis JEPA dan world model generatif? | D19: I, C(Comparison), O
B20: RQ-05 | C20: Apa dataset benchmark dan metrik evaluasi yang umum digunakan komunitas riset untuk mengukur kualitas world model pada kedua pendekatan tersebut? | D20: O, C(Context)
B21: RQ-06 | C21: Apa tantangan terbuka dan arah penelitian masa depan dalam menggabungkan atau memilih antara kedua garis keturunan tersebut dalam pengembangan world model? | D21: I, C(Comparison), C(Context)

Sheet Search_Strategy
B2: Detailed Search Strategy
B3: Document the complete, reproducible search process. Keep the exact query used for every database.
B5: Protocol Item | C5: Value | D5: Guidance
B6: Search Objective | C6: Mengidentifikasi studi yang mengusulkan, mengevaluasi, atau membandingkan arsitektur world model berbasis JEPA dan generatif pada domain video dan simulasi digital, dengan fokus pada tiga tugas hilir (downstream tasks): video/frame prediction, representation probing untuk pemahaman visual/aksi, dan planning/control pada simulasi digital (model-based RL). | D6: State what the search is designed to identify.
B7: Search Period | C7: Januari 2018 - September 2026 | D7: Example: January 2018 – December 2026
B8: Search Date(s) | C8: Akan dicatat saat pelaksanaan pencarian (tahap Conducting), direncanakan pada minggu pertama setelah protokol ini disetujui | D8: Record actual search dates.
B9: Search Queries | C9: ("world model" OR "world models" OR "learned dynamics model" OR "latent dynamics model") AND ("JEPA" OR "joint embedding predictive architecture" OR "I-JEPA" OR "V-JEPA" OR "generative world model" OR "diffusion world model" OR "autoregressive world model") AND ("video prediction" OR "frame prediction" OR "action recognition" OR "probing" OR "planning" OR "model-based RL" OR "model-based reinforcement learning" OR "interactive simulation" OR "virtual environment") | D9: Example: ("intrution detection" OR "intrution detection system" OR "IDS") AND ("machine learning" OR "deep learning")
B10: Publication Type | C10: Hanya artikel jurnal ilmiah (peer-reviewed journal articles). Prosiding konferensi, naskah preprint (arXiv), buku, bab buku, editorial, dan laporan teknis ditolak. | D10: Journal articles, conference papers, etc.
B11: Snowballing | C11: Both (backward dan forward snowballing) dari artikel rujukan kunci (mis. Ha & Schmidhuber, 2018; LeCun, 2022; Assran et al., 2023; Bardes et al., 2024) khusus untuk melacak artikel jurnal ilmiah yang mensitasi atau disitasi oleh karya perintis tersebut. | D11: Backward / forward / both / none
B12: Other Search Methods | C12: Pencarian komplementer melalui Google Scholar untuk melacak artikel jurnal yang belum terindeks di basis data utama; penelusuran manual (hand-searching) pada arsip jurnal terbitan IEEE, ACM, dan ScienceDirect. | D12: Hand-searching, grey literature, websites, etc.
B15: Database Search Log (diisi saat proses conducting)
B17: Database/Source | C17: Platform/URL | D17: Search Date | E17: Exact Search String | F17: Filters / Limits | G17: Results Returned (number of papers) | H17: Notes
B18: Scopus | C18: https://www.scopus.com | D18: 46282 | E18: TITLE-ABS-KEY ( ( "world model" OR "world models" OR "learned dynamics model" OR "latent dynamics model" ) AND ( "JEPA" OR "joint embedding predictive architecture" OR "I-JEPA" OR "V-JEPA" OR "generative world model" OR "diffusion world model" OR "autoregressive world model" ) AND ( "video prediction" OR "frame prediction" OR "action recognition" OR "probing" OR "planning" OR "model-based RL" OR "model-based reinforcement learning" OR "interactive simulation" OR "virtual environment" ) ) AND PUBYEAR > 2017 AND PUBYEAR < 2027 AND DOCTYPE ( ar ) AND LANGUAGE ( english ) | F18: Terintegrasi dalam query string (Years: 2018–2026; Language: English; Document Type: Article) | G18: 6 | H18: Pencarian studi primer jurnal ilmiah peer-reviewed; difokuskan pada tiga downstream tasks sesuai protokol. Ditemukan 6 artikel jurnal yang relevan.
B19: IEEE Xplore | C19: https://ieeexplore.ieee.org | D19: 46282 | E19: ("All Metadata":"world model" OR "All Metadata":"world models" OR "All Metadata":"learned dynamics model" OR "All Metadata":"latent dynamics model") AND ("All Metadata":"JEPA" OR "All Metadata":"joint embedding predictive architecture" OR "All Metadata":"I-JEPA" OR "All Metadata":"V-JEPA" OR "All Metadata":"generative world model" OR "All Metadata":"diffusion world model" OR "All Metadata":"autoregressive world model") AND ("All Metadata":"video prediction" OR "All Metadata":"frame prediction" OR "All Metadata":"action recognition" OR "All Metadata":"probing" OR "All Metadata":"planning" OR "All Metadata":"model-based RL" OR "All Metadata":"model-based reinforcement learning" OR "All Metadata":"interactive simulation" OR "All Metadata":"virtual environment") | F19: Publication Years: 2018–2026 (rentang riil dokumen terjaring: 2022–2026); Content Type: Journals; Field: All Metadata | G19: 2 | H19: Pencarian Command Search pada IEEE Xplore. Seluruh dokumen yang teridentifikasi terbit antara tahun 2022–2026 sehingga otomatis memenuhi batasan periode protokol. Dibatasi ketat pada artikel jurnal ilmiah (menyaring 2 artikel jurnal dan mengeksklusikan 6 prosiding konferensi).
B20: ScienceDirect | C20: ScienceDirect.com | D20: 46283 | E20: ("world model" OR "world models") AND ("JEPA" OR "generative" OR "diffusion") AND ("video prediction" OR "planning" OR "probing") | F20: Field: Title, abstract, author-specified keywords; Years: 2018–2026; Article types: Research articles | G20: 2 | H20: Kueri 3 kluster (Populasi, Mazhab, dan 3 Downstream Tasks) dengan pembatasan 7 operator Boolean bawaan ScienceDirect. Filter dibatasi murni pada Research articles terbitan Elsevier (jurnal Expert Systems with Applications dan Engineering Applications of Artificial Intelligence); buku, bab buku, dan ensiklopedia dieksklusikan.
B21: Google Scholar | C21: https://scholar.google.com/ | D21: 46274 | E21: ("world model" OR "world models" OR "latent dynamics model") AND ("JEPA" OR "joint embedding predictive architecture" OR "I-JEPA" OR "V-JEPA" OR "generative world model" OR "diffusion world model") AND ("video prediction" OR "video generation" OR "interactive simulation") | F21: Rentang tahun (Custom range): 2018-2026; opsi "sertakan paten" tidak dicentang; "mencakup kutipan" dicentang (default Google Scholar) | G21: 1630 | H21: Angka "Sekitar 1.630 hasil" adalah ESTIMASI dari Google Scholar, bukan hitungan presisi seperti Scopus/IEEE (nilai ini diketahui bisa berubah antar-load/halaman). Cakupan Scholar jauh lebih luas dan tidak terkurasi dibanding Scopus/IEEE -- ikut menghitung preprint, tesis, dan laporan non-peer-review -- sehingga 1.630 tidak sebanding langsung dengan 132 (Scopus) atau 5 (IEEE). Sesuai protokol (lihat Other Search Methods), Google Scholar diposisikan sebagai pelengkap/snowballing, bukan sumber utama untuk PRISMA count.
B22: ACM Digital Library | C22: https://dl.acm.org | D22: 46276 | E22: [[All: "world model"] OR [All: "world models"] OR [All: "learned dynamics model"] OR [All: "latent dynamics model"]] AND [[All: "jepa"] OR [All: "joint embedding predictive architecture"] OR [All: "i-jepa"] OR [All: "v-jepa"] OR [All: "generative world model"] OR [All: "diffusion world model"] OR [All: "video generation"] OR [All: "autoregressive video"]] | F22: None (fitur rentang tanggal dibatasi akun premium; batasan tahun 2018–2026 disaring manual saat screening) | G22: 134 | H22: Pencarian pada The ACM Full-Text Collection (861.309 record); 134 dokumen teridentifikasi dan siap diekspor untuk deduplikasi.
B49: Search String Construction
B51: Concept | C51: PICOC Link | D51: Primary Terms | E51: Synonyms / Variants | F51: Final Block
B52: World Model (Dasar) | C52: P | D52: world model | E52: world models; learned dynamics model; latent dynamics model; world modeling | F52: ("world model" OR "world models" OR "learned dynamics model" OR "latent dynamics model")
B53: JEPA Lineage | C53: I | D53: JEPA | E53: joint embedding predictive architecture; I-JEPA; V-JEPA; MC-JEPA | F53: ("JEPA" OR "joint embedding predictive architecture" OR "I-JEPA" OR "V-JEPA")
B54: Generative Lineage | C54: C (Comparison) | D54: generative world model | E54: diffusion world model; autoregressive world model; video diffusion model | F54: ("generative world model" OR "diffusion world model" OR "autoregressive world model")
B55: Downstream Tasks (Outcome) | C55: O | D55: downstream tasks | E55: video prediction; frame prediction; action recognition; representation probing; planning; model-based RL; model-based reinforcement learning | F55: ("video prediction" OR "frame prediction" OR "action recognition" OR "probing" OR "planning" OR "model-based RL" OR "model-based reinforcement learning")
B56: Context (Domain & Simulation) | C56: C (Context) | D56: virtual environment | E56: interactive simulation; digital simulation; visual sequence | F56: ("interactive simulation" OR "virtual environment" OR "visual sequence")
B59: Recommended Search Logic
B61: Within a concept: OR | C61: (term1 OR synonym1 OR synonym2)
B62: Between major concepts: AND | C62: (Population terms) AND (Intervention terms) AND (Outcome terms) | D62: Detailed Search Strategy
B63: Optional concepts | C63: Comparison and Context can be added when they improve precision without unnecessarily excluding relevant studies.

Sheet Protocol_Criteria
B2: Review Protocol & Criteria
B3: Complete this sheet before full screening
B5: Research Question(s) | C5: RQ-01 s/d RQ-06 (lihat sheet PICOC_RQs) - perbandingan arsitektur, objektif pembelajaran, performa prediksi video dan dinamika lingkungan, efisiensi komputasi/sampel, dan tantangan terbuka antara garis keturunan JEPA dan generatif pada world model
B6: Search Databases / Sources | C6: IEEE Xplore, ACM Digital Library, ScienceDirect, Scopus, Google Scholar
B7: Publication Period | C7: Januari 2018 - September 2026
B8: Language | C8: Inggris
B9: Study Type / Design | C9: Hanya artikel jurnal ilmiah peer-reviewed (journal articles) dengan kontribusi arsitektural atau evaluasi empiris yang jelas terhadap world model. Prosiding konferensi, preprint, buku, bab buku, editorial, dan laporan teknis dieksklusi
B10: Inclusion Threshold | C10: Artikel wajib memenuhi IC1, IC2, IC3, dan IC5 (syarat dasar kelayakan). IC4 berfungsi sebagai penguat kualitas/prioritas (bukan syarat wajib), digunakan saat proses Quality Assessment untuk menandai studi dari lab riset utama
B11: Quality Threshold | C11: Default: ≥75% = Final; 60–74.9% = Review; <60% = Exclude. Adapt and justify in your protocol.
B14: Suggested Inclusion Criteria
B16: Code | C16: Criterion
B17: IC1 | C17: Artikel secara langsung mengusulkan, mengevaluasi, atau membandingkan arsitektur world model (berbasis JEPA maupun generatif)
B18: IC2 | C18: Domain aplikasi berkaitan dengan world model pada data video (prediksi video, representasi visual dari observasi berurutan)
B19: IC3 | C19: Diterbitkan dalam rentang Januari 2018 - September 2026
B20: IC4 | C20: Merupakan artikel jurnal atau prosiding konferensi peer-review dari laboratorium riset utama (Meta AI/FAIR, Google DeepMind, NVIDIA Research, dll.)
B21: IC5 | C21: Teks lengkap (full text) tersedia dan berbahasa Inggris
B24: Suggested Exclusion Criteria
B26: Code | C26: Criterion
B27: EC1 | C27: Artikel duplikat yang muncul di lebih dari satu database
B28: EC2 | C28: Diterbitkan di luar rentang periode pencarian (sebelum 2018 atau setelah September 2026)
B29: EC3 | C29: Tidak membahas arsitektur world model atau tidak relevan dengan perbandingan JEPA vs generatif
B30: EC4 | C30: Tidak melibatkan prediksi dinamika lingkungan/dunia (mis. murni pemrosesan bahasa alami tanpa komponen world modeling)
B31: EC5 | C31: Bukan merupakan artikel penuh (hanya abstrak, poster workshop tanpa detail teknis, atau tesis yang belum peer-review)
B32: EC6 | C32: Teks lengkap tidak dapat diakses
B33: EC7 | C33: Merupakan prosiding konferensi, preprint, atau bentuk publikasi non-jurnal lain yang tidak memenuhi kriteria Study Type
B35: Default Quality Assessment Questions
B37: Code | C37: Question
B38: QA1 | C38: Apakah tujuan penelitian/pertanyaan penelitian dinyatakan dengan jelas?
B39: QA2 | C39: Apakah arsitektur world model (JEPA-based atau generative-based) dijelaskan secara jelas, termasuk objektif pembelajaran, input/output, dan representasi laten?
B40: QA3 | C40: Apakah setup eksperimen (dataset, lingkungan simulasi/nyata, baseline pembanding) dijelaskan secara memadai?
B41: QA4 | C41: Apakah metrik evaluasi yang digunakan relevan dengan tugas world modeling (mis. akurasi prediksi, kualitas representasi laten, atau performa pada tugas hilir seperti perencanaan dan prediksi video)?
B42: QA5 | C42: Apakah dilakukan perbandingan terhadap baseline yang relevan, baik dari garis keturunan yang sama maupun garis keturunan lain (JEPA vs generatif)?
B43: QA6 | C43: Apakah hasil penelitian dilaporkan secara jelas dan didukung bukti kuantitatif?
B44: QA7 | C44: Apakah keterbatasan (limitations), kegagalan model, atau ancaman validitas dibahas?
B45: QA8 | C45: Apakah kesimpulan konsisten dengan hasil yang dilaporkan dan memberikan kontribusi baru terhadap diskusi JEPA vs generatif dalam world model?

Sheet Raw_Articles
A1: Article_ID | B1: Source_Type | C1: Database/Source | D1: Search_Date | E1: Search_Query | F1: Title | G1: Authors | H1: Year | I1: Journal/Conference | J1: DOI | K1: URL | L1: Abstract | M1: Document_Type | N1: Language | O1: Duplicate_Key | P1: Duplicate? | Q1: Notes
A2: A0001 | B2: Database | C2: Scopus | D2: 46282 | F2: Intelligent driving foundation model; [智能驾驶大模型] | G2: Hu J.; Huang L.; Zhai W.; Yan R.; Li C.; Zheng W.; He R.; Zha Z.; Xiong H. | H2: 2026 | I2: Journal of Image and Graphics | J2: 10.11834/jig.260085 | K2: https://www.scopus.com/pages/publications/105043177703?origin=resultslist | L2: The intelligent driving foundation model integrates vision, language, and action through multimodal learning, shifting autonomous driving from traditional perception-planning-control architectures toward unified end-to-end systems. It enhances robustness, decision-making, and generalization through unified representation, generative reasoning, and few-shot learning. This review summarizes recent advances in decision planning, environmental perception, visual question answering, and data generation. Large language and multimodal models improve interpretability, semantic understanding, trajectory prediction, and interaction between autonomous vehicles and humans. Visual question answering enables models to explain driving decisions and respond to semantic queries, while retrieval-augmented generation and chain-of-thought techniques further improve reasoning. To address the high cost and limited coverage of driving data, research increasingly focuses on automatic annotation, self-supervised learning, generative data synthesis, and world models. The review also compares international and Chinese developments, highlighting differences in multimodal integration, engineering applications, data systems, and computational optimization. Future research should focus on real-time performance, safety, personalization, trustworthy AI evaluation, open data infrastructure, and human-AI alignment. | M2: Article | N2: English | O2: =IF(F2="","",LOWER(TRIM(F2)&"|"&TRIM(G2)&"|"&H2)) | P2: No
A3: A0002 | B3: Database | C3: Scopus | D3: 46282 | F3: What Drives Success in Physical Planning with Joint-Embedding Predictive World Models? | G3: Terver B.; Yang T.-Y.; Ponce J.; Bardes A.; Cun Y.L. | H3: 2026 | I3: Transactions on Machine Learning Research | J3: - | K3: https://www.scopus.com/pages/publications/105039617137?origin=resultslist | L3: A long-standing challenge in AI is to develop agents capable of solving a wide range of physical tasks and generalizing to new, unseen tasks and environments. A popular recent approach involves training a world model from state-action trajectories and subsequently using it with a planning algorithm to solve new tasks. Planning is commonly performed in the input space, but a recent family of methods has introduced planning algorithms that optimize in the learned representation space of the world model, with the promise that abstracting irrelevant details yields more efficient planning. In this work, we characterize models from this family as JEPA-WMs and investigate the technical choices that make algorithms from this class work. We propose a comprehensive study of several key components with the objective of finding the optimal approach within the family. We conducted experiments using both simulated environments and real-world robotic data, and studied how the model architecture, the training objective, and the planning algorithm affect planning success. We combine our findings to propose a model that outperforms two established baselines, DINO-WM and V-JEPA-2-AC, in both navigation and manipulation tasks. Code, data and checkpoints are available at https://github.com/facebookresearch/jepa-wms. © 2026, Transactions on Machine Learning Research. All rights reserved. | M3: Article | N3: English | O3: =IF(F3="","",LOWER(TRIM(F3)&"|"&TRIM(G3)&"|"&H3)) | P3: No
A4: A0003 | B4: Database | C4: Scopus | D4: 46282 | F4: Structured Dynamics in the Algorithmic Agent | G4: Ruffini G.; Castaldo F.; Vohryzek J. | H4: 2026 | I4: Entropy | J4: 10.3390/e27010090 | K4: https://www.scopus.com/pages/publications/85215784438?origin=resultslist | L4: In the Kolmogorov Theory of Consciousness, algorithmic agents utilize inferred compressive models to track coarse-grained data produced by simplified world models, capturing regularities that structure subjective experience and guide action planning. Here, we study the dynamical aspects of this framework by examining how the requirement of tracking natural data drives the structural and dynamical properties of the agent. We first formalize the notion of a generative model using the language of symmetry from group theory, specifically employing Lie pseudogroups to describe the continuous transformations that characterize invariance in natural data. Then, adopting a generic neural network as a proxy for the agent dynamical system and drawing parallels to Noether’s theorem in physics, we demonstrate that data tracking forces the agent to mirror the symmetry properties of the generative world model. This dual constraint on the agent’s constitutive parameters and dynamical repertoire enforces a hierarchical organization consistent with the manifold hypothesis in the neural network. Our findings bridge perspectives from algorithmic information theory (Kolmogorov complexity, compressive modeling), symmetry (group theory), and dynamics (conservation laws, reduced manifolds), offering insights into the neural correlates of agenthood and structured experience in natural systems, as well as the design of artificial intelligence and computational models of the brain. © 2025 by the authors. | M4: Article | N4: English | O4: =IF(F4="","",LOWER(TRIM(F4)&"|"&TRIM(G4)&"|"&H4)) | P4: No
A5: A0004 | B5: Database | C5: Scopus | D5: 46282 | F5: Hybrid intelligence systems for reliable automation: advancing knowledge work and autonomous operations with scalable AI architectures | G5: Grosvenor A.; Zemlyansky A.; Wahab A.; Bohachov K.; Dogan A.; Deighan D. | H5: 2026 | I5: Frontiers in Robotics and AI | J5: Frontiers in Robotics and AI | K5: https://www.scopus.com/pages/publications/105012031405?origin=resultslist | L5: Introduction: Mission-critical automation demands decision-making that is explainable, adaptive, and scalable—attributes elusive to purely symbolic or data-driven approaches. We introduce a hybrid intelligence (H-I) system that fuses symbolic reasoning with advanced machine learning via a hierarchical architecture, inspired by cognitive frameworks like Global Workspace Theory (Baars, A Cognitive Theory of Consciousness, 1988). Methods: This architecture operates across three levels to achieve autonomous, end-to-end workflows: Navigation: Using Vision Transformers, and graph-based neural networks, the system navigates file systems, databases, and software interfaces with precision. Discrete Actions: Multi-framework automated machine learning (AutoML) trains agents to execute discrete decisions, augmented by Transformers and Joint Embedding Predictive Architectures (JEPA) (Assran et al., 2023, 15619–15629) for complex time-series analysis, such as anomaly detection. Planning: Reinforcement learning, world model-based reinforcement learning, and model predictive control orchestrate adaptive workflows tailored to user requests or live system demands. Results: The system’s capabilities are demonstrated in two mission-critical applications: Space Domain Awareness, Satellite Behavior Detection: A graph-based JEPA paired with multi-agent reinforcement learning enables near real-time anomaly detection across 15,000 on-orbit objects, delivering a precision-recall score of 0.98. Autonomously Driven Simulation Setup: The system autonomously configures Computational Fluid Dynamics (CFD) setups, with an AutoML-driven optimizer enhancing the meshing step—boosting boundary layer capture propagation (BL-CP) from 8% to 98% and cutting geometry failure rates from 88% to 2% on novel aircraft geometries. Scalability is a cornerstone, with the distributed training pipeline achieving linear scaling across 2,000 compute nodes for AI model training, while secure model aggregation incurs less than 4% latency in cross-domain settings. Discussion: By blending symbolic precision with data-driven adaptability, this hybrid intelligence system offers a robust, transferable framework for automating complex knowledge work in domains like space operations and engineering simulations—and adjacent applications such as autonomous energy and industrial facility operations, paving the way for next-generation industrial AI systems. Copyright © 2025 Grosvenor, Zemlyansky, Wahab, Bohachov, Dogan and Deighan. | M5: Article | N5: English | O5: =IF(F5="","",LOWER(TRIM(F5)&"|"&TRIM(G5)&"|"&H5)) | P5: No
A6: A0005 | B6: Database | C6: Scopus | D6: 46282 | F6: World4RL: Diffusion World Models for Policy Refinement with Reinforcement Learning for Robotic Manipulation | G6: Jiang Z.; Liu K.; Qin Y.; Tian S.; Zheng Y.; Zhou M.; Zhang Z.; Yu C.; Li H.; Zhao D. | H6: 2026 | I6: IEEE Robotics and Automation Letters | J6: 10.1109/LRA.2026.3728345 | K6: https://www.scopus.com/pages/publications/105050194365?origin=resultslist | L6: Robotic manipulation policies are commonly initialized through imitation learning, but their performance is limited by the scarcity and narrow coverage of expert data. Reinforcement learning can refine policies to alleviate this limitation, yet real-robot training is costly and unsafe, while training in simulators suffers from the sim-to-real gap. Recent advances in generative models have demonstrated remarkable capabilities in real-world simulation, with diffusion models in particular excelling at generation. This raises the question of how diffusion model-based world models can be combined to enhance pre-trained policies in robotic manipulation. In this work, we propose World4RL, a two-stage system-level framework for robotic manipulation that uses a frozen diffusion visual world model as an imagined environment for reinforcement-learning-based policy refinement. Unlike prior works that primarily employ world models for planning, our framework enables direct end-to-end policy optimization. World4RL is designed around two principles: pre-training a diffusion world model that captures diverse dynamics on multi-task datasets and refining policies entirely within a frozen world model to avoid online real-world interactions. Extensive simulation and real-world experiments demonstrate that World4RL provides high-fidelity environment modeling and enables consistent policy refinement, yielding significantly higher success rates compared to imitation learning and other baselines. © 2016 IEEE. | M6: Article | N6: English | O6: =IF(F6="","",LOWER(TRIM(F6)&"|"&TRIM(G6)&"|"&H6)) | P6: Yes
A7: A0006 | B7: Database | C7: Scopus | D7: 46282 | F7: Generative World Modeling for Risk-Aware Autonomous UAV Navigation in Dynamic Traffic Networks | G7: Momani A.M.; Alsekait D.M.; Al-Khasawneh M.A.; Othman S.H.; Al-Tarawneh I.; Sharma N.; Khoh W.H. | H7: 2026 | I7: Computers, Materials and Continua | J7: 10.32604/cmc.2026.082572 | K7: https://www.scopus.com/pages/publications/105046080515?origin=resultslist | L7: Unmanned Aerial Vehicles (UAVs) are finding more and more applications in logistics, surveillance, and other operations at a large scale. However, autonomous navigation in dynamic traffic situations is not an easy task due to limited energy, moving obstacles, and inter-agent interactions. The proposed paper can be discussed as a Generative World Modeling (GWM) framework of risk-focused UAV navigation in the dynamic traffic network. This paper proposes a GWM framework for risk-aware UAV navigation in dynamic traffic networks. The proposed design incorporates three key elements; a generative world model for predicting future environmental conditions, a diffusion-based trajectory-generation component that generates multiple possible paths, and a risk-aware decision-making component that selects trajectories based on energy use, collision avoidance, and mission criteria. The framework is also extended to the case of a multi-UAV swarm, where a coordinated swarm is facilitated by shared representations in the latent space to alleviate potential conflicts. The experimental analysis of real-world-inspired UAV trajectory data indicates that the proposed GWM framework outperforms the classical, reinforcement-based, and conflict-aware baseline approaches across a range of performance metrics, including mission success rate, delivery time, energy cost, safety, and path efficiency. The findings indicate that with risk-sensitive and generative prediction, autonomous UAV missions should be more robust, effective, and secure in uncertain, complex environments. Copyright © 2026 The Authors. | M7: Article | N7: English | O7: =IF(F7="","",LOWER(TRIM(F7)&"|"&TRIM(G7)&"|"&H7)) | P7: No
A8: A0007 | B8: Database | C8: IEEE Xplore | D8: 46282 | F8: Offline Inverse Constrained Reinforcement Learning for Safe-Critical Decision Making in Healthcare | G8: N. Fang; G. Liu; W. Gong | H8: 2026 | I8: IEEE Transactions on Artificial Intelligence | J8: 10.1109/TAI.2025.3610390 | K8: https://ieeexplore.ieee.org/document/11168453 | L8: One important application of reinforcement learning (RL) is optimizing treatment decisions in healthcare. However, a naïve RL policy can lead to unsafe medical decisions, such as excessive dosages or abrupt treatment changes, often because agents fail to account for common-sense constraints. To mitigate these problems, constrained reinforcement learning (CRL) naturally emerges as a promising approach for safer decision-making by optimizing policies under predefined constraints. To extend CRL to healthcare applications, a fundamental challenge lies in accurately specifying the constraint function for different healthcare scenarios. Recent inverse constrained reinforcement learning (ICRL) is a promising approach that infers constraints from expert demonstrations. However, ICRL algorithms model Markovian decisions and rely on real-time interactive environments. These settings do not align with the practical requirement of a decision-making system in healthcare, where decisions rely on historical treatment recorded in an offline dataset. To tackle these issues, we propose the constraint transformer (CT). Specifically, 1) we utilize a causal attention mechanism to incorporate historical decisions and observations into the constraint modeling, while employing a non-Markovian layer for weighted constraints to capture critical states. 2) A generative world model is used for exploratory data augmentation, enabling offline RL methods to simulate unsafe decision sequences. In multiple medical scenarios, empirical results demonstrate that CT can capture unsafe states and achieve strategies that approximate lower mortality rates, reducing the occurrence probability of unsafe behaviors. | M8: Journal Article | N8: English | O8: =IF(F8="","",LOWER(TRIM(F8)&"|"&TRIM(G8)&"|"&H8)) | P8: No
A9: A0008 | B9: Database | C9: IEEE Xplore | D9: 46282 | F9: World4RL: Diffusion World Models for Policy Refinement With Reinforcement Learning for Robotic Manipulation | G9: Z. Jiang; K. Liu; Y. Qin; S. Tian; Y. Zheng; M. Zhou; Z. Zhang; C. Yu; H. Li; D. Zhao | H9: 2026 | I9: IEEE Robotics and Automation Letters | J9: 10.1109/LRA.2026.3728345 | K9: https://ieeexplore.ieee.org/document/11668663 | L9: Robotic manipulation policies are commonly initialized through imitation learning, but their performance is limited by the scarcity and narrow coverage of expert data. Reinforcement learning can refine policies to alleviate this limitation, yet real-robot training is costly and unsafe, while training in simulators suffers from the sim-to-real gap. Recent advances in generative models have demonstrated remarkable capabilities in real-world simulation, with diffusion models in particular excelling at generation. This raises the question of how diffusion model-based world models can be combined to enhance pre-trained policies in robotic manipulation. In this work, we propose World4RL, a two-stage system-level framework for robotic manipulation that uses a frozen diffusion visual world model as an imagined environment for reinforcement-learning-based policy refinement. Unlike prior works that primarily employ world models for planning, our framework enables direct end-to-end policy optimization. World4RL is designed around two principles: pre-training a diffusion world model that captures diverse dynamics on multi-task datasets and refining policies entirely within a frozen world model to avoid online real-world interactions. Extensive simulation and real-world experiments demonstrate that World4RL provides high-fidelity environment modeling and enables consistent policy refinement, yielding significantly higher success rates compared to imitation learning and other baselines. © 2016 IEEE. | M9: Journal Article | N9: English | O9: =IF(F9="","",LOWER(TRIM(F9)&"|"&TRIM(G9)&"|"&H9)) | P9: Yes
A10: A0009 | B10: Database | C10: ScienceDirect | D10: 46283 | E10: ("world model" OR "world models") AND ("JEPA" OR "generative" OR "diffusion") AND ("video prediction" OR "planning" OR "probing") | F10: Large language model-based planning agent with generative memory strengthens performance in textualized world | G10: Liu, Junyang; Hao, Wenning; Cheng, Kai; Jin, Dawei | H10: 2025 | I10: Engineering Applications of Artificial Intelligence | J10: 10.1016/j.engappai.2025.110319 | K10: https://www.sciencedirect.com/science/article/pii/S0952197625003197 | L10: This paper constructs a planning agent with generative memory (GM-Agent) based on Large Language Models (LLM) to address the complex planning problems in textualized world. GM-Agent perceives and makes decisions by representing the world as a quintuple, constructing a textualized world model (TWM), and generating memory. Its generative rewards and strategies can optimize the decision-making performance. Baseline results demonstrate that under the LandWar benchmark, compared with prompt-based generative agents and the traditional Reinforcement Learning from Human Feedback (RLHF) framework, GM-Agent can exhibit stronger continuous planning capabilities. The degree to which GM-Agent follows instructions has increased by 137.25%, and the degree to which its decisions are aligned with human experience has increased by 51.69%. The execution ability of mainline tasks and the convergence performance of the model demonstrate state-of-the-arts (SOTA). In comparisons with various benchmark artificial intelligences (AIs), GM-Agent performs excellently, especially showing obvious advantages in adversarial tasks, with a maximum 96.08% improvement in the performance of mainline tasks. Orthogonal experiments prove the effectiveness of the proposed reward scoring and advantage function. We have demonstrated the framework portability and application scenario generalization capabilities of GM-Agent in different LLM frameworks and benchmarks in different fields. It shows excellent performance in the complex field of embodied intelligence planning. However, there is still a certain gap compared with advanced technologies in scientific common sense and logical reasoning tasks. We have demonstrated the application potential of GM-Agent in multiple application scenarios, and found its deficiencies in terms of stability, observation subjectivity, feedback ability, and flexibility. | M10: Research article | N10: English | O10: liu2025large | P10: No | Q10: Hasil pencarian primer ScienceDirect. Berfokus pada textualized world model (TWM) dan LLM. Catatan awal untuk tahap screening: berpotensi dieksklusi pada kriteria EC4 karena domain berupa teks, bukan sekuens visual/video.
A11: A0010 | B11: Database | C11: ScienceDirect | D11: 46283 | E11: ("world model" OR "world models") AND ("JEPA" OR "generative" OR "diffusion") AND ("video prediction" OR "planning" OR "probing") | F11: Automation of PCB autorouting via world-model reinforcement learning and freerouting integration | G11: Liao, Yin-Chi; Pan, Sheng-Xin; Chiang, Po-Jui | H11: 2026 | I11: Expert Systems with Applications | J11: 10.1016/j.eswa.2026.131424 | K11: https://www.sciencedirect.com/science/article/pii/S0957417426003374 | L11: We present DreamerV3+FR, a model-based reinforcement learning framework that automates Printed Circuit Board (PCB) routing by integrating a latent world model with the FreeRouting environment. Unlike traditional model-free approaches, our system utilizes latent imagination to simulate multi-step trajectories and optimize net ordering before physical execution, significantly reducing exploration costs and ensuring geometric validity. Empirical evaluation establishes a new state-of-the-art: the framework achieves a 96% completion rate and reduces training time by 21% compared to Deep Q-Networks (DQN). Furthermore, we identify a scalability bottleneck in competing paradigms: while model-free methods like Proximal Policy Optimization (PPO)) fail to adapt to the sparse-reward setting, Generative AI (VAE+GAN) and Large Language Model (LLM) agents falter due to probabilistic design rule violations and spatial hallucinations respectively. In contrast, our world-model approach successfully generalizes to unseen 6-layer PCBs, maintaining 97.6% Signal/Power Integrity (SI/PI) efficiency where others collapse. With a ~50× reduction in design iteration time compared to manual workflows and the lowest recorded rework rate, the proposed framework offers a robust, scalable foundation for end-to-end electronic design automation. [https://github.com/yinqimakeitfun/dreamer-Autorouting/tree/main](https://github.com/yinqimakeitfun/dreamer-Autorouting/tree/main) | M11: Research article | N11: English | O11: liao2026automation | P11: No
A12: A0011 | B12: Database | C12: OpenAlex | D12: 46287 | E12: Multiple queries (Q1-Q10) | F12: Understanding World or Predicting Future? A Comprehensive Survey of World Models | G12: Jingtao Ding; Yunke Zhang; Yu Shang; Y. Zhang; Zefang Zong; Jie Feng; Yuan Yuan; Hongyuan Su; Nian Li; Nicholas Sukiennik; Fengli Xu; Yong Li | H12: 2025 | I12: ACM Computing Surveys | J12: 10.1145/3746449 | K12: https://doi.org/10.1145/3746449 | L12: The concept of world models has garnered significant attention due to advancements in multimodal large language models such as GPT-4 and video generation models such as Sora, which are central to the pursuit of artificial general intelligence. This survey offers a comprehensive review of the literature on world models. Generally, world models are regarded as tools for either understanding the present state of the world or predicting its future dynamics. This review presents a systematic categorization of world models, emphasizing two primary functions: (1) constructing internal representations to understand the mechanisms of the world, and (2) predicting future states to simulate and guide decision-making. Initially, we examine the current progress in these two categories. We then explore the application of world models in key domains, including autonomous driving, robotics, and social simulacra, with a focus on how each domain utilizes these aspects. Finally, we outline key challenges and provide insights into potential future research directions. We summarize the representative articles along with their code repositories in https://github.com/tsinghua-fib-lab/World-Model . | M12: article | N12: en | O12: =IF(F12="","",LOWER(TRIM(F12)&"|"&TRIM(G12)&"|"&H12)) | P12: No | Q12: Citations: 57
A13: A0012 | B13: Database | C13: OpenAlex | D13: 46287 | E13: Multiple queries (Q1-Q10) | F13: Prospective Role of Foundation Models in Advancing Autonomous Vehicles | G13: Jianhua Wu; Bingzhao Gao; Jincheng Gao; Jianhao Yu; Hongqing Chu; Qiankun Yu; Xun Gong; Yi Chang; H. Eric Tseng; Hong Chen; Jie Chen | H13: 2024 | I13: Research | J13: 10.34133/research.0399 | K13: https://doi.org/10.34133/research.0399 | L13: With the development of artificial intelligence and breakthroughs in deep learning, large-scale foundation models (FMs), such as generative pre-trained transformer (GPT), Sora, etc., have achieved remarkable results in many fields including natural language processing and computer vision. The application of FMs in autonomous driving holds considerable promise. For example, they can contribute to enhancing scene understanding and reasoning. By pre-training on rich linguistic and visual data, FMs can understand and interpret various elements in a driving scene, and provide cognitive reasoning to give linguistic and action instructions for driving decisions and planning. Furthermore, FMs can augment data based on the understanding of driving scenarios to provide feasible scenes of those rare occurrences in the long tail distribution that are unlikely to be encountered during routine driving and data collection. The enhancement can subsequently lead to improvement in the accuracy and reliability of autonomous driving systems. Another testament to the potential of FMs' applications lies in world models, exemplified by the DREAMER series, which showcases the ability to comprehend physical laws and dynamics. Learning from massive data under the paradigm of self-supervised learning, world models can generate unseen yet plausible driving environments, facilitating the enhancement in the prediction of road users' behaviors and the off-line training of driving strategies. In this paper, we synthesize the applications and future trends of FMs in autonomous driving. By utilizing the powerful capabilities of FMs, we strive to tackle the potential issues stemming from the long-tail distribution in autonomous driving, consequently advancing overall safety in this domain. | M13: article | N13: en | O13: =IF(F13="","",LOWER(TRIM(F13)&"|"&TRIM(G13)&"|"&H13)) | P13: No | Q13: Citations: 20
A14: A0013 | B14: Database | C14: OpenAlex | D14: 46287 | E14: Multiple queries (Q1-Q10) | F14: When Remote Sensing Meets Foundation Model: A Survey and Beyond | G14: Chunlei Huo; Keming Chen; Shuaihao Zhang; Zeyu Wang; Heyu Yan; Jing Shen; Yu Hong; G. R. Qi; Hongmei Fang; Zihan Wang | H14: 2025 | I14: Remote Sensing | J14: 10.3390/rs17020179 | K14: https://doi.org/10.3390/rs17020179 | L14: Most deep-learning-based vision tasks rely heavily on crowd-labeled data, and a deep neural network (DNN) is usually impacted by the laborious and time-consuming labeling paradigm. Recently, foundation models (FMs) have been presented to learn richer features from multi-modal data. Moreover, a single foundation model enables zero-shot predictions on various vision tasks. The above advantages make foundation models better suited for remote sensing images, where image annotations are more sparse. However, the inherent differences between natural images and remote sensing images hinder the applications of the foundation model. In this context, this paper provides a comprehensive review of common foundation models and domain-specific foundation models for remote sensing, and it summarizes the latest advances in vision foundation models, textually prompted foundation models, visually prompted foundation models, and heterogeneous foundation models. Despite the great potential of foundation models for vision tasks, open challenges concerning data, model, and task impact the performance of remote sensing images and make foundation models far from practical applications. To address open challenges and reduce the performance gap between natural images and remote sensing images, this paper discusses open challenges and suggests potential directions for future advancements. | M14: article | N14: en | O14: =IF(F14="","",LOWER(TRIM(F14)&"|"&TRIM(G14)&"|"&H14)) | P14: No | Q14: Citations: 47
A15: A0014 | B15: Database | C15: OpenAlex | D15: 46287 | E15: Multiple queries (Q1-Q10) | F15: A Survey on Vision--Language--Action Models for Embodied AI | G15: Yueen Ma; Zixing Song; Yuzheng Zhuang; Jianye Hao; Irwin King | H15: 2026 | I15: IEEE Transactions on Neural Networks and Learning Systems | J15: 10.1109/tnnls.2025.3650584 | K15: https://doi.org/10.1109/tnnls.2025.3650584 | L15: Embodied AI is widely recognized as a cornerstone of artificial general intelligence (AGI) because it involves controlling embodied agents to perform tasks in the physical world. Building on the success of large language models (LLMs) and vision-language models (VLMs), a new category of multimodal models-referred to as vision-language-action (VLA) models-has emerged to address language-conditioned robotic tasks in embodied AI by leveraging their distinct ability to generate actions. The recent proliferation of VLAs necessitates a comprehensive survey to capture the rapidly evolving landscape. To this end, we present the first survey on VLAs for embodied AI. This work provides a detailed taxonomy of VLAs, organized into three major lines of research. The first line focuses on individual components of VLAs. The second line is dedicated to developing VLA-based control policies adept at predicting low-level actions. The third line comprises high-level task planners capable of decomposing long-horizon tasks into a sequence of subtasks, thereby guiding VLAs to follow more general user instructions. Furthermore, we provide an extensive summary of relevant resources, including datasets, simulators, and benchmarks. Finally, we discuss the challenges facing VLAs and outline promising future directions in embodied AI. A curated repository associated with this survey is available at: https://github.com/yueen-ma/Awesome-VLA. | M15: article | N15: en | O15: =IF(F15="","",LOWER(TRIM(F15)&"|"&TRIM(G15)&"|"&H15)) | P15: No | Q15: Citations: 29
A16: A0015 | B16: Database | C16: OpenAlex | D16: 46287 | E16: Multiple queries (Q1-Q10) | F16: Towards Generalist Robot Learning from Internet Video: A Survey | G16: Robert McCarthy; Daniel C. H. Tan; Dominik Schmidt; Fernando Acero; Nathan Herr; Yilun Du; Thomas George Thuruthel; Zhibin Li | H16: 2025 | I16: Journal of Artificial Intelligence Research | J16: 10.1613/jair.1.17400 | K16: https://doi.org/10.1613/jair.1.17400 | L16: Scaling deep learning to massive and diverse internet data has driven remarkable breakthroughs in domains such as video generation and natural language processing. Robot learning, however, has thus far failed to replicate this success and remains constrained by a scarcity of available data. Learning from Videos (LfV) methods aim to address this data bottleneck by augmenting traditional robot data with large-scale internet video. This video data provides foundational information regarding physical dynamics, behaviours, and tasks, and can be highly informative for general-purpose robots. This survey systematically examines the emerging field of LfV. We first outline essential concepts, including detailing fundamental LfV challenges such as distribution shift and missing action labels in video data. Next, we comprehensively review current methods for extracting knowledge from large-scale internet video, overcoming LfV challenges, and improving robot learning through video-informed training. The survey concludes with a critical discussion of future opportunities. Here, we emphasize the need for scalable foundation model approaches that can leverage the full range of available internet video and enhance the learning of robot policies and dynamics models. Overall, the survey aims to inform and catalyse future LfV research, driving progress towards general-purpose robots. | M16: article | N16: en | O16: =IF(F16="","",LOWER(TRIM(F16)&"|"&TRIM(G16)&"|"&H16)) | P16: No | Q16: Citations: 8
A17: A0016 | B17: Database | C17: OpenAlex | D17: 46287 | E17: Multiple queries (Q1-Q10) | F17: Research on World Models for Connected Automated Driving: Advances, Challenges, and Outlook | G17: Nuo Chen; Xiang Liu | H17: 2025 | I17: Applied Sciences | J17: 10.3390/app15168986 | K17: https://doi.org/10.3390/app15168986 | L17: Connected Autonomous Vehicles (CAVs) technology holds immense potential for enhancing traffic safety and efficiency; however, its inherent complexity presents significant challenges for conventional autonomous driving. World Models (WMs), an advanced deep learning paradigm, offer an innovative approach to address these CAV challenges by learning environmental dynamics and precisely predicting future states. This survey systematically reviews the advancements of WMs in connected automated driving, delving into the key methodologies and technological breakthroughs across six core application domains: cooperative perception, prediction, decision-making, control, human–machine collaboration, and scene generation. Furthermore, this paper critically analyzes the current limitations of WMs in CAV scenarios, particularly concerning multi-source heterogeneous data fusion, physical law mapping, long-term temporal memory, and cross-scenario generalization capabilities. Building upon this analysis, we prospectively outline future research directions aimed at fostering the development of more robust, efficient, and interpretable WMs. Ultimately, this work aims to provide a crucial reference for constructing safe, efficient, and sustainable connected automated driving systems. | M17: article | N17: en | O17: =IF(F17="","",LOWER(TRIM(F17)&"|"&TRIM(G17)&"|"&H17)) | P17: No | Q17: Citations: 3
A18: A0017 | B18: Database | C18: OpenAlex | D18: 46287 | E18: Multiple queries (Q1-Q10) | F18: When Does Sora Show: The Beginning of TAO to Imaginative Intelligence and Scenarios Engineering | G18: Fei–Yue Wang; Qinghai Miao; Lingxi Li; Qinghua Ni; Xuan Li; Juanjuan Li; Lili Fan; Yonglin Tian; Qing‐Long Han | H18: 2024 | I18: IEEE/CAA Journal of Automatica Sinica | J18: 10.1109/jas.2024.124383 | K18: https://doi.org/10.1109/jas.2024.124383 | L18: During our discussion at workshops for writing “What Does ChatGPT Say: The DAO from Algorithmic Intelligence to Linguistic Intelligence” [1], we had expected the next milestone for Artificial Intelligence (AI) would be in the direction of Imaginative Intelligence (II), i.e., something similar to automatic words-to-videos generation or intelligent digital movies/theater technology that could be used for conducting new “Artificiofactual Experiments” [2] to replace conventional “Counterfactual Experiments” in scientific research and technical development for both natural and social studies [2]–[6]. Now we have OpenAI's Sora, so soon, but this is not the final, actually far away, and it is just the beginning. | M18: article | N18: en | O18: =IF(F18="","",LOWER(TRIM(F18)&"|"&TRIM(G18)&"|"&H18)) | P18: No | Q18: Citations: 63
A19: A0018 | B19: Database | C19: OpenAlex | D19: 46287 | E19: Multiple queries (Q1-Q10) | F19: Latent Prediction-Based Generative Semantic Communication for Video Transmission in Wireless Networks | G19: Maheshi Lokumarambage; Thushan Sivalingam; Feng Dong; Nandana Rajatheva; Anil Fernando | H19: 2026 | I19: IEEE Open Journal of the Communications Society | J19: 10.1109/ojcoms.2026.3684230 | K19: https://doi.org/10.1109/ojcoms.2026.3684230 | L19: The increasing dominance of video traffic in intelligent sensing and control applications introduces a major challenge to the capacity limits of modern wireless networks. Classical information theory defines fixed physical boundaries on channel capacity, beyond which further improvement requires rethinking what information is transmitted. Semantic communication (SemCom) bridges this by only sending the semantics of the intended message. This paper presents a SemCom framework that leverages latent-space procedural video prediction with world-model-guided temporal dynamics. Instead of transmitting pixel data, the transmitter encodes high-level semantic representations of context frames and sends them through the physical channel. A temporal transformer predicts future latent states at the receiver. The framework jointly optimizes perceptual, adversarial, and temporal objectives to preserve both visual quality and trajectory consistency under channel impairments. Experiments conducted on video sequences of the BAIR robot pushing dataset demonstrate that the proposed method achieves lower normalized endpoint and velocity errors compared to learned baseline real-time intermediate flow estimation (RIFE) + better portable graphics (BPG) with reduced bit-rate compared to traditional codecs. The results indicate that incorporating temporal dynamics as semantics into the communication process enables efficient and anticipatory video transmission suitable for applications such as tele-robotic, underwater, and autonomous systems. | M19: article | N19: en | O19: =IF(F19="","",LOWER(TRIM(F19)&"|"&TRIM(G19)&"|"&H19)) | P19: No | Q19: Citations: 1
A20: A0019 | B20: Database | C20: OpenAlex | D20: 46287 | E20: Multiple queries (Q1-Q10) | F20: Generative emergent communication: large language model is a collective world model | G20: Tadahiro Taniguchi; Ryo Ueda; Tomoaki Nakamura; Masahiro Suzuki; Akira Taniguchi | H20: 2026 | I20: Advanced Robotics | J20: 10.1080/01691864.2026.2661958 | K20: https://doi.org/10.1080/01691864.2026.2661958 | L20: This survey and perspective paper addresses a fundamental puzzle: how Large Language Models (LLMs) acquire extensive world knowledge without direct sensorimotor experience. We introduce the Collective World Model hypothesis, arguing that an LLM does not learn a world model from scratch. Instead, it learns a statistical approximation of a collective world model already implicitly encoded in human language through a society-wide process of embodied, interactive sense-making. To formalize this process, we introduce the generative emergent communication (Generative EmCom) framework, built upon Collective Predictive Coding (CPC). This framework models language emergence as decentralized Bayesian inference, effectively creating an encoder-decoder structure at a societal scale: human society collectively encodes its grounded representations into language, and an LLM decodes these symbols to reconstruct a latent space mirroring the original structure. This perspective offers a principled explanation for how LLMs acquire their capabilities. We formalize the Generative EmCom framework, connecting it to world models and multi-agent reinforcement learning, and apply it to interpret LLMs, explaining phenomena like distributional semantics as a natural consequence of representation reconstruction. This work provides a unified theory that bridges individual cognitive development, collective language evolution, and the foundations of large-scale AI. | M20: article | N20: en | O20: =IF(F20="","",LOWER(TRIM(F20)&"|"&TRIM(G20)&"|"&H20)) | P20: No | Q20: Citations: 2
A21: A0020 | B21: Database | C21: OpenAlex | D21: 46287 | E21: Multiple queries (Q1-Q10) | F21: Scaling up self-supervised learning for improved surgical foundation models | G21: Tim J. M. Jaspers; Ronald L. P. D. de Jong; Yiping Li; Carolus H. J. Kusters; Franciscus H. A. Bakker; Romy C. van Jaarsveld; Gino M. Kuiper; Richard van Hillegersberg; Jelle P. Ruurda; Willem M. Brinkman; Josien P. W. Pluim; Peter H. N. de With; Marcel Breeuwer; Yasmina Al Khalil; Fons van der Sommen | H21: 2025 | I21: Medical Image Analysis | J21: 10.1016/j.media.2025.103873 | K21: https://doi.org/10.1016/j.media.2025.103873 | L21: • Demonstration of effectiveness of SSL for surgical computer vision using the largest dataset reported to date. • Strong generalization and robust evaluation are shown across six surgical datasets, four procedures, and three tasks, outperforming current SOTA foundation models. • Providing insights into large-scale SSL for surgical computer vision in terms of scaling, pretraining time, dataset composition, and model architecture. • Release of the models and a curated dataset of 2.1 million surgical video frames, establishing a critical resource for advancing surgical foundation model training Foundation models have revolutionized computer vision by achieving vastly superior performance across diverse tasks through large-scale pretraining on extensive datasets. However, their application in surgical computer vision has been limited. This study addresses this gap by introducing SurgeNetXL, a novel surgical foundation model that sets a new benchmark in surgical computer vision. Trained on the largest reported surgical dataset to date, comprising over 4.7 million video frames, SurgeNetXL achieves consistent top-tier performance across six datasets spanning four surgical procedures and three tasks, including semantic segmentation, surgical phase recognition, and critical view of safety (CVS) classification. Compared with the best-performing surgical foundation model, SurgeNetXL shows mean improvements of 4.0%, 8.9%, and 11.4% for semantic segmentation, phase recognition, and CVS classification, respectively. Additionally, SurgeNetXL outperforms ImageNet1k by 16.1%, 8.0%, and 4.3% for the respective tasks. In addition to advancing model performance, this study provides key insights into scaling pretraining datasets, extending training durations, and optimizing model architectures specifically for surgical computer vision. These findings pave the way for improved generalization and robustness in data-scarce scenarios, offering a comprehensive framework for future research in this domain. All models and a subset of the SurgeNetXL dataset, including over 2 million video frames, are publicly available at: https://github.com/TimJaspers0801/SurgeNet . | M21: article | N21: en | O21: =IF(F21="","",LOWER(TRIM(F21)&"|"&TRIM(G21)&"|"&H21)) | P21: No | Q21: Citations: 10
A22: A0021 | B22: Database | C22: OpenAlex | D22: 46287 | E22: Multiple queries (Q1-Q10) | F22: Shifting the retinal foundation models paradigm from slices to volumes for optical coherence tomography | G22: Raphael Judkiewicz; Eran Berkowitz; Meishar Meisel; Tomer Michaeli; Joachim A. Behar | H22: 2026 | I22: npj Digital Medicine | J22: 10.1038/s41746-026-02496-7 | K22: https://doi.org/10.1038/s41746-026-02496-7 | L22: Optical Coherence Tomography (OCT) is essential in ophthalmology for cross-sectional imaging of the retina. Pretrained foundation models facilitate task-specific model development by enabling fine-tuning with limited labeled data. However, current foundation models rely on a single B-scan (usually the central slice), overlooking volumetric context. This research investigates video foundation models to capture full 3D retinal structure and improve diagnostic performance. V-JEPA, a state-of-the-art video foundation model, was benchmarked against retinal foundation models (RETFound, VisionFM) and a natural image foundation model (DINOv2). All were fine-tuned to detect Age-related Macular Degeneration or Glaucomatous Optic Neuropathy using five OCT datasets. V-JEPA consistently equaled or outperformed image-based models, achieving an average AUROC of 0.94 (0.80-0.99), versus 0.90 (0.76-0.98) for the best image model, a statistically significant improvement (p < 0.001). To our knowledge, this is the first application of transformer-based video models to volumetric OCT, highlighting their promise in 3D medical imaging. | M22: article | N22: en | O22: =IF(F22="","",LOWER(TRIM(F22)&"|"&TRIM(G22)&"|"&H22)) | P22: No | Q22: Citations: 2
A23: A0022 | B23: Database | C23: OpenAlex | D23: 46287 | E23: Multiple queries (Q1-Q10) | F23: Foundation Models in Remote Sensing: Evolving from unimodality to multimodality | G23: Danfeng Hong; Chenyu Li; Xuyang Li; Gustau Camps-Valls; Jocelyn Chanussot | H23: 2026 | I23: IEEE Geoscience and Remote Sensing Magazine | J23: 10.1109/mgrs.2026.3669086 | K23: https://doi.org/10.1109/mgrs.2026.3669086 | L23: Remote sensing (RS) techniques are increasingly crucial for deepening our understanding of the planet. As the volume and diversity of RS data continue to grow exponentially, there is an urgent need for advanced data modeling and understanding capabilities to manage and interpret these vast datasets effectively. Foundation models present significant new growth opportunities and immense potential to revolutionize the RS field. In this paper, we conduct a comprehensive technical survey on foundation models in RS, offering a brand-new perspective by exploring their evolution from unimodality to multimodality. We hope this work serves as a valuable entry point for researchers interested in both foundation models and RS and helps them launch new projects or explore new research topics in this rapidly evolving area. This survey addresses the following three key questions: What are foundation models in RS? Why are foundation models needed in RS? How can we effectively guide junior researchers in gaining a comprehensive and practical understanding of foundation models in RS applications? More specifically, we begin by outlining the background and motivation, emphasizing the importance of foundation models in RS. We then review existing foundation models in RS, systematically categorizing them into unimodal and multimodal approaches. Additionally, we provide a tutorial-like section to guide researchers, especially beginners, on how to train foundation models in RS and apply them to real-world tasks. The survey aims to equip researchers in RS with a deeper and more efficient understanding of foundation models, enabling them to get started easily and effectively apply these models across various RS applications. | M23: article | O23: =IF(F23="","",LOWER(TRIM(F23)&"|"&TRIM(G23)&"|"&H23)) | P23: No | Q23: Citations: 8
A24: A0023 | B24: Database | C24: OpenAlex | D24: 46287 | E24: Multiple queries (Q1-Q10) | F24: Towards efficient real-time video motion transfer via generative time series modeling | G24: Tasmiah Haque; Md Asif Bin Syed; Byungheon Jeong; Xue Bai; Sumit Mohan; Somdyuti Paul; Imtiaz Ahmed; Srinjoy Das | H24: 2026 | I24: Multimedia Tools and Applications | J24: 10.1007/s11042-026-21138-4 | K24: https://doi.org/10.1007/s11042-026-21138-4 | L24: Motion Transfer is an Artificial Intelligence (AI) technique that synthesizes videos by transferring motion dynamics from a driving video to a source image. In this work we propose a deep learning-based framework to enable real-time video motion transfer which is critical for enabling bandwidth-efficient applications such as video conferencing, remote health monitoring, virtual reality interaction, and vision-based anomaly detection. This is done using keypoints which serve as semantically meaningful, compact representations of motion across time, and are extracted from every video frame via a self-supervised detector. To enable bandwidth savings during video transmission we perform forecasting of keypoints using two generative time series models–Variational Recurrent Neural Networks (VRNN) and Gated Recurrent Units with Normalizing Flows (GRU-NF)–enabling both single and diverse future prediction modes. The predicted keypoints are transformed into realistic video frames using an optical flow-based module paired with a generator network, thereby facilitating accurate video forecasting and enabling efficient, low-frame-rate video transmission. Based on the application this allows the framework to either generate a deterministic future sequence or sample a diverse set of plausible futures. Experimental results across three benchmark video datasets using state-of-the-art quality and diversity metrics for video animation and reconstruction tasks demonstrate that VRNN achieves the best point-forecast fidelity (lowest MAE) in the majority of evaluated settings in applications requiring stable and accurate multi-step forecasting (e.g., video conferencing, remote patient monitoring) and is particularly competitive in higher-uncertainty, multi-modal settings. This is achieved by utilizing the superior reconstruction property of the Variational Autoencoder and by introducing recurrently conditioned stochastic latent variables that carry past contexts to capture uncertainty and temporal variation. On the other hand the GRU-NF model enables richer diversity of generated videos while maintaining high visual quality to better support tasks like AI-driven anomaly detection. This is realized by learning an invertible, exact-likelihood mapping between the keypoints and their latent representations which supports rich and controllable sampling of diverse yet coherent keypoint sequences. Our work lays the foundation for next-generation AI systems that require real-time, bandwidth-efficient, and semantically controllable video generation, with broad implications for communication, health, and manufacturing applications. The code is available at: https://github.com/Tasmiah1408028/RealtimeVideoMotionTransfer | M24: article | N24: en | O24: =IF(F24="","",LOWER(TRIM(F24)&"|"&TRIM(G24)&"|"&H24)) | P24: No | Q24: Citations: 1
A25: A0024 | B25: Database | C25: OpenAlex | D25: 46287 | E25: Multiple queries (Q1-Q10) | F25: The generative revolution: AI foundation models in geospatial health—applications, challenges and future research | G25: Bernd Resch; Polychronis Kolokoussis; David Hanny; Maria Antonia Brovelli; Maged N. Kamel Boulos | H25: 2025 | I25: International Journal of Health Geographics | J25: 10.1186/s12942-025-00391-0 | K25: https://doi.org/10.1186/s12942-025-00391-0 | L25: In an era of rapid technological advancements, generative artificial intelligence and foundation models are reshaping industries and offering new advanced solutions in a wide range of scientific areas, particularly in public and environmental health. However, foundation models have previously mostly focused on understanding and generating text, while geospatial features, interrelations, flows and correlations have been neglected. Thus, this paper outlines the importance of research into Geospatial Foundation Models, which have the potential to revolutionise digital health surveillance and public health. We examine the latest advances, opportunities, challenges, and ethical considerations of geospatial foundation models for research and applications in digital health. We focus on the specific challenges of integrating geospatial context with foundation models and lay out the future potential for multimodal geospatial foundation models for a variety of research avenues in digital health surveillance and health assessment. | M25: article | N25: en | O25: =IF(F25="","",LOWER(TRIM(F25)&"|"&TRIM(G25)&"|"&H25)) | P25: No | Q25: Citations: 10
A26: A0025 | B26: Database | C26: OpenAlex | D26: 46287 | E26: Multiple queries (Q1-Q10) | F26: Trajectory generative models: a survey from unconditional and conditional perspectives | G26: Weiping Zhu; Renhe Jiang; Dongyuan Li; Xiangjie Kong; Xuan Song | H26: 2025 | I26: GeoInformatica | J26: 10.1007/s10707-025-00558-8 | K26: https://doi.org/10.1007/s10707-025-00558-8 | L26: Abstract Trajectories serve as a cornerstone of intelligent transportation systems, playing an important role in many applications such as traffic flow prediction, route planning, and urban management. However, the availability of such data is limited due to privacy issues, ethical concerns, and the high cost associated with infrastructure deployment. In recent years, rapidly developing generative models such as Variational Autoencoders (VAEs), Generative Adversarial Networks (GANs), and Diffusion Models (DMs) have demonstrated strong capabilities in learning complex data distributions and generating synthetic data, thereby alleviating the data accessibility issue. In this survey, we systematically review the existing literature on deep generative models that address the problem of trajectory generation. First, we classify the existing literature into two categories: unconditional and conditional trajectory generation. In unconditional generation, trajectories are generated without contextual constraints, whereas conditional generation incorporates several important factors such as road network topology, time of day, and user preferences to guide the trajectory generation process. Then, for each category, we further classify the literature into three methodological types, including VAEs, GANs, and DMs, and analyze how these models address key challenges under different settings. Finally, we discuss promising directions for future research and hope to inspire further advances in trajectory generation. | M26: article | N26: en | O26: =IF(F26="","",LOWER(TRIM(F26)&"|"&TRIM(G26)&"|"&H26)) | P26: No | Q26: Citations: 6
A27: A0026 | B27: Database | C27: OpenAlex | D27: 46287 | E27: Multiple queries (Q1-Q10) | F27: Visual prediction method based on time series-driven LSTM model | G27: Huxidan Jumahong; Yongjie Wang; Abuduwaili Aili; Weina Wang | H27: 2025 | I27: Scientific Reports | J27: 10.1038/s41598-025-21911-9 | K27: https://doi.org/10.1038/s41598-025-21911-9 | L27: Significant progress has been made in time series prediction and image processing problems. However, most of the studies have focused on either the field of time series or image processing separately, failing to integrate the advantages of both fields. To overcome the limitations of existing algorithms in image temporal inference, this paper proposes a novel visual prediction framework based on the time series forecasting model, which can predict single-frame or multi-frame images by thoroughly analyzing their spatio-temporal features. Firstly, the ViT image feature extraction module is constructed by randomly masking and reconstructing the image to analyze the learned image and extract the features. Then, the time series construction module is designed to convert the extracted features into the time series model suitable for the LSTM network. Finally, the time series data is predicted based on LSTM, and the predicted time series data is transformed into the predicted image. A series of experiments is done on three types of cloud image datasets. The results are analyzed superficially and demonstrate the effectiveness and feasibility of the proposed method in terms of image prediction performance. | M27: article | N27: en | O27: =IF(F27="","",LOWER(TRIM(F27)&"|"&TRIM(G27)&"|"&H27)) | P27: No | Q27: Citations: 1
A28: A0027 | B28: Database | C28: OpenAlex | D28: 46287 | E28: Multiple queries (Q1-Q10) | F28: Deep Learning and Attention-Based Methods for Human Activity Recognition and Anticipation: A Comprehensive Review | G28: Md Rezowan Shuvo; M. S. Mekala; Eyad Elyan | H28: 2025 | I28: Cognitive Computation | J28: 10.1007/s12559-025-10513-2 | K28: https://doi.org/10.1007/s12559-025-10513-2 | L28: Abstract In recent years, there has been a significant increase in research focused on Human Activity Analysis (HAA). This field has progressed from basic activity recognition tasks to addressing more challenging ones, such as predicting future human actions based on partially observed videos and even predicting actions before they happen. The evolution of HAA has been driven by recent advancements in attention-based models like Transformers, along with a wide range of applications from security surveillance to advanced monitoring systems, behaviour analysis, and more. A comprehensive review of HAA literature from 2017 to 2025, with a novel taxonomy emphasising activity recognition, prediction, and anticipation, is presented. We critically review and examine recognition methods from trimmed and untrimmed videos, context-aware and trajectory-based prediction, and short-term and long-term anticipation. Through a comprehensive analysis, we review and evaluate key aspects of this domain, including attention-based contextual comprehension, temporal dynamics modelling, and multi-model fusion methods. Furthermore, we critically examine and assess the public datasets utilised in driving this research forward, pinpointing limitations and primary challenges within this domain. Finally, the paper provides a summary of recent developments in HAA and suggests future directions, with the hope that it will serve as a valuable reference for researchers in the field. | M28: article | N28: en | O28: =IF(F28="","",LOWER(TRIM(F28)&"|"&TRIM(G28)&"|"&H28)) | P28: No | Q28: Citations: 8
A29: A0028 | B29: Database | C29: OpenAlex | D29: 46287 | E29: Multiple queries (Q1-Q10) | F29: Learning Abstractions: A Conversation with Yann LeCun | G29: Yann LeCun; James Manyika | H29: 2026 | I29: Daedalus | J29: 10.1162/daed.a.972 | K29: https://doi.org/10.1162/daed.a.972 | L29: James Manyika. Yann LeCun is widely considered one of the godfathers of the modern era of artificial intelligence. His pioneering research with Geoffrey Hinton and Yoshua Bengio on deep learning won them the 2018 Turing Award, considered the Nobel Prize for computer science, and in 2025, the three were awarded the Queen Elizabeth Prize for Engineering. Yann has long focused on foundational and scientific advances in AI, from biologically inspired convolutional neural networks and graph transformer networks to energy-based models for machine learning and world models. In this dialogue, we focus on foundational advances in AI, what he sees as progress to date, the limitations of current mainstream approaches, and what's needed to further advance AI and benefit science, including the role of scientists and the importance of open science.Manyika. The last decade in artificial intelligence has been extraordinary. How would you characterize the progress? What has surprised you?Yann LeCun. I'm actually going to go back fifteen years to when Geoffrey Hinton, Yoshua Bengio, and I were trying to rekindle interest in neural networks, which we rebranded as “deep learning.” And we were struck by how fast it was adopted: within eighteen months of the first papers showing that deep learning could improve speech recognition, basically every mobile speech recognition system was using a neural network.1 This was my first exposure to how quickly technology is widely adopted when it actually brings something to the table.There was a similar phenomenon in 2013 when convolutional neural networks became the rage for image recognition. Within months they were widely deployed, and people got excited about the prospect of driving assistance and autonomous driving. Within a few years, we had automatic emergency braking systems in cars, all using convolutional neural networks. These systems have become mandatory in Europe, leading to a 40 percent reduction in frontal collisions.2 This technology was saving lives, and it made me proud.The year 2015 was more about natural language processing (NLP). Yoshua's lab made people pay attention to attention mechanisms, which direct deep-learning models to focus their attention on the most relevant data.3 Then “Attention Is All You Need,” which introduced the transformer architecture, surprised quite a few by building large networks as stacks of associative memory modules based on so-called self-attention that compares inputs to each other.4 I had been advocating for self-supervised learning (SSL) for many years, but I did not expect that its success would be primarily in NLP - though we had hints that “shallow” SSL worked for text embedding, with Word2vec from Google and fastText at Meta.5 Then there was BERT from Google, which used transformers and attention instead of recurrent neural networks, which a lot of us suspected would not go very far.6I wasn't particularly interested in NLP myself, but it was certainly a very useful thing to do. What I found surprising was that a simple form of temporal prediction works so well for text. I had been working on temporal prediction for video for at least ten years before that, hoping that if you train a system to predict what's going to happen in a video, it will understand how the world works: that the world is three dimensional and that objects move independently, for example. Some objects are inanimate and obey laws that are relatively easy to understand and make predictions about. Animated objects are much more difficult to predict. The hope and the whole idea of SSL is that by training a system through prediction, it can understand the underlying structure of what it is trained on. I was focusing on video because I believe that if we can do video, we can do everything. As it turns out, SSL from video is much harder than from text.Manyika. As you think about where we are with the development of AI's capabilities, are there scientific disciplines you're most excited for AI to help make breakthrough advances?LeCun. Certainly. Materials science, chemistry, biochemistry, and proteins are major topics. In medicine, can we understand and cure chronic diseases or cancers? Predicting protein structure is major progress, but the next step is designing proteins with particular properties.7 Can we build predictive mesoscopic AI models for complex systems like organelles, cells, or pathways in cells that are too complex for a single human to understand? The same applies to new materials and chemical compounds for improving energy storage (like batteries) or for catalysis (such as separating hydrogen from oxygen to store electrical energy as methane).Importantly, the models that work well for proteins are really specialized; they're not generic models. There is a hope that in the future we'll come up with models that are more generic, that can make wider sets of predictions. This includes efficient prediction in large systems controlled by partial differential | M29: article | N29: en | O29: =IF(F29="","",LOWER(TRIM(F29)&"|"&TRIM(G29)&"|"&H29)) | P29: No | Q29: Citations: 1
A30: A0029 | B30: Database | C30: OpenAlex | D30: 46287 | E30: Multiple queries (Q1-Q10) | F30: Shaping future sustainable cities with AI-powered urban informatics: Toward human-AI symbiosis | G30: Yang Yue; Guang Yan; Tian Lan; Rui Cao; Qili Gao; Wenxiu Gao; Bo Huang; Guan Huang; Zhengdong Huang; Zihan Kan; Xiangyang Li; Dong Liu; Xintao Liu; Ding Ma; Lili Wang; Jizhe Xia; Xiaochun Yang; Meng Zhou; Anthony Gar‐On Yeh; Renzhong Guo; Christophe Claramunt | H30: 2025 | I30: Computational Urban Science | J30: 10.1007/s43762-025-00190-0 | K30: https://doi.org/10.1007/s43762-025-00190-0 | L30: Abstract The rapid evolution of Artificial Intelligence (AI) has ushered in a transformative era for urban studies, moving beyond traditional analytical methods to advanced Deep Learning architectures, with Transformers model in the spotlight. Yet, unlike bioinformatics, which has successfully utilised AI to decode static biological systems, or cheminformatics, which optimises chemical synthesis, urban informatics grappled with human-centric complexity that encompass subjective perceptions, socio-political dynamics, and multifaceted challenges that defy deterministic solutions. To avoid techno-solutionist pitfalls, we convened an interdisciplinary group of scholars to explore AI-powered urban informatics and proposed a Human-AI Symbiosis framework to foster sustainable cities and advance urban research. This Opinion paper synthesises insights into four key research directions, focusing on the evolving landscape of urban informatics and its potential to drive innovation in sustainable cities, policy-making, and societal development. | M30: article | N30: en | O30: =IF(F30="","",LOWER(TRIM(F30)&"|"&TRIM(G30)&"|"&H30)) | P30: No | Q30: Citations: 21
A31: A0030 | B31: Database | C31: OpenAlex | D31: 46287 | E31: Multiple queries (Q1-Q10) | F31: Evaluating Intelligent CPTED Systems to Support Crime Prevention Decision-Making in Municipal Control Centers | G31: Woochul Choi; Joonyeop Na; Sang-Kyeong Lee | H31: 2024 | I31: Applied Sciences | J31: 10.3390/app14156581 | K31: https://doi.org/10.3390/app14156581 | L31: To maximize its synergetic effect across the cycle from prevention to response to post-crime management, crime prevention requires a balanced combination of spatial urban design and advanced crime prevention technologies for crime prediction and real-time response. This study derived intelligent Crime Prevention Through Environmental Design (CPTED) services and suggested a decision model based on the fuzzy Technique for Order Preference by Similarity to Ideal Solution (TOPSIS) to implement these services in municipal control centers. The analysis results are summarized as follows. First, this study established a fuzzy TOPSIS-based decision-making support model enabling local government control centers to effectively select intelligent CPTED service elements. Second, overall, operator-led Closed-Circuit Television (CCTV) and platform control technologies were identified as significant components of intelligent CPTED service elements. Third, a comparison by city size revealed that large cities in the Seoul metropolitan area rated system services for control based on advanced crime prevention infrastructure (e.g., the crime monitoring systems and real-time control drones/robots) relatively higher. In contrast, small and medium-sized cities in other provinces rated services that were perceptible to residents and improved crime-prone environments (e.g., artificial intelligence (AI) video analysis for living safety) relatively higher. | M31: article | N31: en | O31: =IF(F31="","",LOWER(TRIM(F31)&"|"&TRIM(G31)&"|"&H31)) | P31: No | Q31: Citations: 6
A32: A0031 | B32: Database | C32: OpenAlex | D32: 46287 | E32: Multiple queries (Q1-Q10) | F32: Onboard Deployment of Remote Sensing Foundation Models: A Comprehensive Review of Architecture, Optimization, and Hardware | G32: Hanbo Sang; Liang Zhang; Tianrui Chen; Weiwei Guo; Zenghui Zhang | H32: 2026 | I32: Remote Sensing | J32: 10.3390/rs18020298 | K32: https://doi.org/10.3390/rs18020298 | L32: With the rapid growth of multimodal remote sensing (RS) data, there is an increasing demand for intelligent onboard computing to alleviate the transmission and latency bottlenecks of traditional orbit-to-ground downlinking workflows. While many lightweight AI algorithms have been widely developed and deployed for onboard inference, their limited generalization capability restricts performance under the diverse and dynamic conditions of advanced Earth observation. Recent advances in remote sensing foundation models (RSFMs) offer a promising solution by providing pretrained representations with strong adaptability across diverse tasks and modalities. However, the deployment of RSFMs onboard resource-constrained devices such as nano satellites remains a significant challenge due to strict limitations in memory, energy, computation, and radiation tolerance. To this end, this review proposes the first comprehensive survey of onboard RSFMs deployment, where a unified deployment pipeline including RSFMs development, model compression techniques, and hardware optimization is introduced and surveyed in detail. Available hardware platforms are also discussed and compared, based on which some typical case studies for low Earth orbit (LEO) CubeSats are presented to analyze the feasibility of onboard RSFMs’ deployment. To conclude, this review aims to serve as a practical roadmap for future research on the deployment of RSFMs on edge devices, bridging the gap between the large-scale RSFMs and the resource constraints of spaceborne platforms for onboard computing. | M32: article | N32: en | O32: =IF(F32="","",LOWER(TRIM(F32)&"|"&TRIM(G32)&"|"&H32)) | P32: No | Q32: Citations: 3
A33: A0032 | B33: Database | C33: OpenAlex | D33: 46287 | E33: Multiple queries (Q1-Q10) | F33: The Phenomenon and Development of K-Pop: The Relationship between Success Factors of K-Pop and the National Image, Social Network Service Citizenship Behavior, and Tourist Behavioral Intention | G33: Joon-ho Kim; Kwang‐Jin Kim; Bum-tae Park; Hyun-ju Choi | H33: 2022 | I33: Sustainability | J33: 10.3390/su14063200 | K33: https://doi.org/10.3390/su14063200 | L33: This study aims to understand the impact of six success factors of K-pop on the national image of Korea perceived by global viewers and SNS citizenship behavior. In addition, this study seeks to validate the impact of the national image of Korea/SNS citizenship behavior, as defined in the foregoing, on tourist behavioral intention. Our analysis was conducted within the theoretical frameworks of the SERVQUAL, Image Theory, and the Theory of Planned Behavior. To that end, 1247 global viewers (eight countries) who have listened, watched and searched for information on K-pop are surveyed. Four statistical programs (SPSS/SmartPLS/GSCA Pro/JASP) are used for regression analysis and structural equation modeling. The results indicate the following. (1) Four K-pop success factors (producers, casting, producing/promotion, and contents) demonstrate a statistically significant positive influence on national image. (2) Two K-pop success factors (casting and producing/promotion) demonstrate a statistically significant positive influence on SNS citizenship behavior. In addition, K-pop contents has a statistically significant positive influence on SNS citizenship behavior (only in SPSS). (3) National image has a statistically significant positive influence on SNS citizenship behavior; and national image and SNS citizenship behavior have a statistically significant positive influence on tourist behavioral intention. As an exemplary cultural product, K-pop is creating economic added value. It is necessary to establish the measures to integrate K-pop in product planning and PR for sustainable marketing for Hallyu tourism. | M33: article | N33: en | O33: =IF(F33="","",LOWER(TRIM(F33)&"|"&TRIM(G33)&"|"&H33)) | P33: No | Q33: Citations: 29
A34: A0033 | B34: Database | C34: OpenAlex | D34: 46287 | E34: Multiple queries (Q1-Q10) | F34: Adapting frozen foundation models for montage-agnostic high-resolution EEG event segmentation | G34: Jun Ma; Tuukka Ruotsalo | H34: 2026 | I34: Journal of Neural Engineering | J34: 10.1088/1741-2552/ae6142 | K34: https://doi.org/10.1088/1741-2552/ae6142 | L34: Abstract Objective. Deploying brain–computer interfaces (BCIs) outside controlled laboratories requires detecting neural events in continuous electroencephalography (EEG) without relying on time-locked synchronization, while simultaneously generalizing across the diverse electrode montages encountered with different acquisition hardware. We investigate whether frozen EEG foundation models can be adapted to perform high temporal resolution event segmentation across unseen montages and datasets without subject-specific calibration. Approach. We introduce a lightweight, parameter-efficient preprocessing layer that interpolates learned channel embeddings based on electrode coordinates, enabling any frozen foundation model backbone to accept arbitrary montages. A shallow segmentation head is attached to produce a label every 4 ms of continuous EEG, and overlapping predictions are consolidated via sliding-window majority voting. Main results. Evaluated on eight public corpora spanning P300, steady-state visually evoked potential and motor imagery paradigms, our method consistently outperforms the original foundation models (BIOT, EEGPT) and classical baselines (EEGNet), achieving a mean macro F 1 of 0.492 and intersection over union (IoU) of 0.361 in cross-subject evaluation, and F 1 = 0.462, IoU = 0.319 in calibration-free cross-dataset generalization. Significance. By decoupling the electrode montage from the pre-trained feature extractor through a plug-in adapter rather than massive retraining, our framework enables practical, resource-efficient BCI applications that operate without time-locked synchronization or montage-specific calibration, laying the groundwork for bridging the lab-to-field gap. The code and pre-processed datasets are available at: https://github.com/yefllower/montage-agnostic-eeg-segmentation . | M34: article | N34: en | O34: =IF(F34="","",LOWER(TRIM(F34)&"|"&TRIM(G34)&"|"&H34)) | P34: No | Q34: Citations: 1
A35: A0034 | B35: Database | C35: OpenAlex | D35: 46287 | E35: Multiple queries (Q1-Q10) | F35: Gen-JEMA: enhanced explainability using generative joint embedding multimodal alignment for monitoring directed energy deposition | G35: José Ferreira; Roya Darabi; Armando Sousa; Frank Brueckner; Luís Paulo Reis; Ana Reis; João Manuel R. S. Tavares; João Sousa | H35: 2025 | I35: Journal of Intelligent Manufacturing | J35: 10.1007/s10845-025-02614-4 | K35: https://doi.org/10.1007/s10845-025-02614-4 | L35: Abstract This work introduces Gen-JEMA, a generative approach based on joint embedding with multimodal alignment (JEMA), to enhance feature extraction in the embedding space and improve the explainability of its predictions. Gen-JEMA addresses these challenges by leveraging multimodal data, including multi-view images and metadata such as process parameters, to learn transferable semantic representations. Gen-JEMA enables more explainable and enriched predictions by learning a decoder from the embedding. This novel co-learning framework, tailored for directed energy deposition (DED), integrates multiple data sources to learn a unified data representation and predict melt pool images from the primary sensor. The proposed approach enables real-time process monitoring using only the primary modality, simplifying hardware requirements and reducing computational overhead. The effectiveness of Gen-JEMA for DED process monitoring was evaluated, focusing on its generalization to downstream tasks such as melt pool geometry prediction and the generation of external melt pool representations using off-axis sensor data. To generate these external representations, autoencoder (AE) and variational autoencoder (VAE) architectures were optimized using Bayesian optimization. The AE outperformed other approaches achieving a 38% improvement in melt pool geometry prediction compared to the baseline and 88% in data generation compared with the VAE. The proposed framework establishes the foundation for integrating multisensor data with metadata through a generative approach, enabling various downstream tasks within the DED domain and achieving a small embedding, allowing efficient process control based on model predictions and embeddings. | M35: article | N35: en | O35: =IF(F35="","",LOWER(TRIM(F35)&"|"&TRIM(G35)&"|"&H35)) | P35: No | Q35: Citations: 5
... A41: A0040 | B41: Database | C41: OpenAlex | D41: 46287 | E41: Multiple queries (Q1-Q10) | F41: SAM–Attention Synergistic Enhancement: SAR Image Object Detection Method Based on Visual Large Model | G41: Yirong Yuan; Jie Yang; Lei Shi; Lingli Zhao | H41: 2025 | I41: Remote Sensing | J41: 10.3390/rs17193311 | K41: https://doi.org/10.3390/rs17193311 | L41: The object detection model for synthetic aperture radar (SAR) images needs to have strong generalization ability and more stable detection performance due to the complex scattering mechanism, high sensitivity of the orientation angle, and susceptibility to speckle noise. Visual large models possess strong generalization capabilities for natural image processing, but their application to SAR imagery remains relatively rare. This paper attempts to introduce a visual large model into the SAR object detection task, aiming to alleviate the problems of weak cross-domain generalization and poor adaptability to few-shot samples caused by the characteristics of SAR images in existing models. The proposed model comprises an image encoder, an attention module, and a detection decoder. The image encoder leverages the pre-trained Segment Anything Model (SAM) for effective feature extraction from SAR images. An Adaptive Channel Interactive Attention (ACIA) module is introduced to suppress SAR speckle noise. Further, a Dynamic Tandem Attention (DTA) mechanism is proposed in the decoder to integrate scale perception, spatial focusing, and task adaptation, while decoupling classification from detection for improved accuracy. Leveraging the strong representational and few-shot adaptation capabilities of large pre-trained models, this study evaluates their cross-domain and few-shot detection performance on SAR imagery. For cross-domain detection, the model was trained on AIR-SARShip-1.0 and tested on SSDD, achieving an mAP50 of 0.54. For few-shot detection on SAR-AIRcraft-1.0, using only 10% of the training samples, the model reached an mAP50 of 0.503. | M41: article | N41: en | O41: =IF(F41="","",LOWER(TRIM(F41)&"|"&TRIM(G41)&"|"&H41)) | P41: No | Q41: Citations: 1
A42: A0041 | B42: Database | C42: OpenAlex | D42: 46287 | E42: Multiple queries (Q1-Q10) | F42: Arkhon: Hamiltonian State Space Duality for Physics-Informed Multimodal World Models | G42: Yani Meziani | H42: 2026 | I42: Zenodo (CERN European Organization for Nuclear Research) | J42: 10.5281/zenodo.18205387 | K42: https://doi.org/10.5281/zenodo.18205387 | L42: PREPRINT: Unofficial Release of the ARKHON Architecture. We present ARKHON (formerly Project Akasha), a state-of-the-art multimodal architecture that integrates Hamiltonian State Space Duality (H-SSD) with Visual-Language Joint Embedding Predictive Architecture (VL-JEPA). The system leverages the Mamba-3 Selective State Space Model (SSM) augmented by a Sparse Mixture of Hamiltonian Experts (SMoE-HE) that enforces latent physical conservation laws through symplectic integration. For visual synthesis, we introduce Hamiltonian Flow Matching (HFM) and persistent 3D Gaussian Splatting (3DGS), enabling ultra-low latency (<50ms) on mobile hardware. This work establishes a new paradigm in latent world models, achieving unprecedented spatiotemporal coherence through a holographic memory architecture. Key Contributions: Physics-Informed Latent Space: Enforcing conservation laws significantly improves long-horizon consistency. Speed: 4× faster visual synthesis than diffusion models; 3-18× inference speedup over transformer baselines. Efficiency: Achieves state-of-the-art video prediction (FVD: 287) on consumer-grade hardware. 📂 FILE STRUCTURE (Included in this Record): 1. ARKHON_Main_Paper.pdf The primary manuscript detailing the H-SSD methodology, benchmark results (FVD/Latency), and comparison against Diffusion Transformers (DiT). 2. ARKHON_Technical_Appendix.pdf Supplementary material containing: - Mathematical proofs for Symplectic Integration in Latent Space. - Full architecture diagrams for the Mamba-3 blocks. Hyperparameters an d ablation studies. | M42: article | O42: =IF(F42="","",LOWER(TRIM(F42)&"|"&TRIM(G42)&"|"&H42)) | P42: No | Q42: Citations: 0
A43: A0042 | B43: Database | C43: OpenAlex | D43: 46287 | E43: Multiple queries (Q1-Q10) | F43: Object Detection and Scene Perception for Connected and Autonomous Vehicles Using LM-JEPA | G43: Abhishek Gupta; Ajmery Sultana | H43: 2026 | I43: Sensors | J43: 10.3390/s26154894 | K43: https://doi.org/10.3390/s26154894 | L43: This paper presents the latent model-joint embedding predictive architecture (LM-JEPA), a resource-efficient collaborative perception framework for connected and autonomous vehicles that integrates latent predictive representation learning with lightweight multi-modal reasoning. Autonomous driving in urban and highway environments requires accurate scene understanding under strict latency, energy, and communication constraints, limiting the practicality of large language model (LLM) and vision-language model (VLM)-based approaches in edge deployments. To address this, LM-JEPA encodes heterogeneous inputs including camera, LiDAR, radar, and map data into a unified latent space using a joint embedding predictive architecture, enabling efficient perception and reasoning without token-level inference. Unlike existing latent-space learning approaches that primarily learn predictive visual embeddings for single-modal perception, the proposed framework integrates multi-modal latent reasoning and adaptive sensor fusion to support collaborative perception under resource-constrained vehicular edge environments. The collaborative perception framework introduces a context-adaptive multi-modal fusion mechanism that dynamically weights sensor and model contributions, along with selective latent transmission and adaptive decoding for resource-aware operation. A lightweight VLM is integrated with an edge-assisted vehicular pipeline to support real-time on-vehicle inference with adaptive offloading based on latency and energy constraints, while a latent-space reasoning module enables cooperative decision-making. Experiments on BDD100K and nuScenes-QA show that LM-JEPA improves perception accuracy by 5% and reduces latency by approximately 7% over LLM and VLM baselines, while achieving up to 25% improvement in scene understanding, 20% higher intersection success rates, improved highway merging, and approximately 15% reduction in the transmitted model parameters. | M43: article | N43: en | O43: =IF(F43="","",LOWER(TRIM(F43)&"|"&TRIM(G43)&"|"&H43)) | P43: No | Q43: Citations: 0
A44: A0043 | B44: Database | C44: OpenAlex | D44: 46287 | E44: Multiple queries (Q1-Q10) | F44: Will power-seeking AGIs harm human society? | G44: Maomei Wang | H44: 2025 | I44: AI & Society | J44: 10.1007/s00146-025-02572-8 | K44: https://doi.org/10.1007/s00146-025-02572-8 | L44: Abstract Many have argued, based on the Instrumental Convergence Thesis, that Artificial General Intelligences (AGIs) will exhibit power-seeking behavior. Such behavior, they warn, could harm human society and pose existential threats—namely, the risk of human extinction or the permanent collapse of civilization. These arguments often rely on an implicit and underexamined assumption: that AGIs will develop world models—internal representations of world dynamics—that resemble those of humans. We challenge this assumption. We argue that once the anthropomorphic assumption—that AGIs’ world models will mirror our own—is rejected, it becomes unclear whether AGIs would pursue the types of power commonly emphasized in the literature, or any familiar types of power at all. This analysis casts doubt on the strength of existing arguments linking the Instrumental Convergence Thesis to existential threats. Moreover, it reveals a deeper layer of uncertainty. AGIs with non-human world models may identify novel or unanticipated types of power that fall outside existing taxonomies, thereby posing underappreciated risks. We further argue that world model alignment—an issue largely overlooked in comparison with value alignment—should be recognized as a core dimension of AI alignment. We conclude by outlining several open questions to inform and guide future research. | M44: article | N44: en | O44: =IF(F44="","",LOWER(TRIM(F44)&"|"&TRIM(G44)&"|"&H44)) | P44: No | Q44: Citations: 1
A45: A0044 | B45: Database | C45: OpenAlex | D45: 46287 | E45: Multiple queries (Q1-Q10) | F45: Epistemic limits of local interpretability in self-modulating cognitive architectures | G45: Abdelaali Mahrouk | H45: 2025 | I45: Frontiers in Artificial Intelligence | J45: 10.3389/frai.2025.1677528 | K45: https://doi.org/10.3389/frai.2025.1677528 | L45: Introduction: Local interpretability methods such as LIME and SHAP are widely used to explain model decisions. However, they rely on assumptions of local continuity that often fail in recursive, self-modulating cognitive architectures. Methods: We analyze the limitations of local proxy models through formal reasoning, simulation experiments, and epistemological framing. We introduce constructs such as Modular Cognitive Attention (MCA), the Cognitive Leap Operator (Ψ), and the Internal Narrative Generator (ING). Results: Our findings show that local perturbations yield divergent interpretive outcomes depending on internal cognitive states. Narrative coherence emerges from recursive policy dynamics, and traditional attribution methods fail to capture bifurcation points in decision space. Discussion: We argue for a shift from post-hoc local approximations to embedded narrative-based interpretability. This reframing supports epistemic transparency in future AGI systems and aligns with cognitive theories of understanding. | M45: article | N45: en | O45: =IF(F45="","",LOWER(TRIM(F45)&"|"&TRIM(G45)&"|"&H45)) | P45: No | Q45: Citations: 3
A46: A0045 | B46: Database | C46: OpenAlex | D46: 46287 | E46: Multiple queries (Q1-Q10) | F46: Beyond Next-Token Prediction: A Standards-Aligned Survey of Autoregressive LLM Failure Modes, Deployment Patterns, and the Potential Role of World Models | G46: Lorenzo Ricciardi Celsi; James McCann | H46: 2026 | I46: Electronics | J46: 10.3390/electronics15050966 | K46: https://doi.org/10.3390/electronics15050966 | L46: This paper is a focused, standards-aligned survey of where autoregressive (AR) large language models (LLMs) tend to break down when deployed inside industrial informatics workflows that must satisfy long-horizon objectives, hard constraints, traceability, and functional-safety obligations (e.g., IEC 61508/ISO 26262/ISO 21448). Rather than claiming new algorithms or experiments, we synthesize and organize prior work into (i) a control-oriented taxonomy of four AR failure modes that recur in practice (compounding error, myopic objectives, data brittleness/hallucinations, and scaling/latency inefficiencies), (ii) a catalog of standards-compatible deployment patterns that mitigate these issues (human-gated LLM-in-the-loop, retrieval + verification pipelines, planner-of-record architectures, and runtime assurance envelopes), and (iii) an operational decision framework (criteria table with observable proxies, a stepwise decision procedure, and worked examples) for deciding when token-centric mitigations are sufficient versus when state/world-model components become warranted. Joint Embedding Predictive Architectures (JEPA) and Hierarchical JEPA (H-JEPA) JEPA are proposed as representative state-predictive architectures, with discussion explicitly bounded by currently available empirical evidence; we explicitly note that the published evidence base is currently concentrated on vision/multimodal benchmarks and that industrial control validation remains limited. To make evidence boundaries transparent, we introduce (a) a survey method (scope, inclusion/exclusion criteria, and data-extraction fields), (b) a comparison matrix across representative prior systems, and (c) an evidence map that links each deployment pattern to peer-reviewed empirical findings and system reports. | M46: article | N46: en | O46: =IF(F46="","",LOWER(TRIM(F46)&"|"&TRIM(G46)&"|"&H46)) | P46: No | Q46: Citations: 0
A47: A0046 | B47: Database | C47: OpenAlex | D47: 46287 | E47: Multiple queries (Q1-Q10) | F47: Layered Intelligence Theory in the Logic of Reality: A Process-Logical Case for Deeply Human and Deeply AI Cognition | G47: Richard Dobson | H47: 2026 | I47: Journal of Cognitive Computing and Extended Realities | J47: 10.65157/jccer.2026.029 | K47: https://doi.org/10.65157/jccer.2026.029 | L47: Layered Intelligence Theory (LIT) is introduced as a process-logical framework grounded in Logic in Reality. The paper presents a dual Deeply Human–Deeply AI programme that unifies deeply human and deeply AI cognition through five nested, dialectically interdependent layers (physiological, emotional, associative, symbolic, integrative). It derives eight architectural design principles and four falsifiable predictions for cognitive systems that preserve human creativity markers while avoiding narrow expertise and taming. | M47: article | O47: =IF(F47="","",LOWER(TRIM(F47)&"|"&TRIM(G47)&"|"&H47)) | P47: No | Q47: Citations: 1
A48: A0047 | B48: Database | C48: OpenAlex | D48: 46287 | E48: Multiple queries (Q1-Q10) | F48: Can World Foundation Models Generate Realistic Driving Videos? A Case Study on Pedestrian Crossing Scenarios | G48: Cong Zhou; Lu Qian; Safraz Ahmed; Olivier Haas; Vasile Palade | H48: 2026 | I48: Electronics | J48: 10.3390/electronics15143033 | K48: https://doi.org/10.3390/electronics15143033 | L48: Autonomous vehicle (AV) technologies have advanced rapidly in recent years, driving an increasing demand for large-scale, high-quality annotated data. However, collecting and annotating real-world pedestrian video datasets is time-consuming, costly, and often insufficient to cover rare and safety-critical scenarios. Recent world foundation models have demonstrated impressive capabilities in generating realistic videos, yet their suitability for safety-critical autonomous driving applications remains largely unexplored. In this work, we investigate whether current world foundation models can generate driving scenarios that are sufficiently realistic and behaviourally consistent for autonomous driving research. We conduct a case study centred on pedestrian–vehicle interactions captured from ego-vehicle dashcam viewpoints, where subtle behavioural and geometric errors can have significant safety implications. To support this investigation, we develop SynPeDAS, an open research framework comprising a collection of synthetic pedestrian-interaction videos, a reusable generation pipeline for transforming real-world driving footage into synthetic scenarios, an automated evaluation suite, and downstream demonstration code. Through quantitative evaluation and structured human assessment, we identify several recurring failure modes, including dynamic misalignment, depth drift, and object persistence inconsistencies. More importantly, we find that commonly used evaluation metrics frequently exhibit ceiling effects and weak alignment with human judgement, limiting their ability to detect safety-critical behavioural errors. These findings indicate that, despite high perceptual realism at the frame level, current generative world models and existing evaluation methodologies remain insufficient for capturing physically grounded motion and task-critical semantics. Consequently, significant challenges remain before world model-generated videos can be considered reliable for safety-critical autonomous driving applications. SynPeDAS provides an open platform for systematically studying these challenges and developing improved generation and evaluation methods. | M48: article | N48: en | O48: =IF(F48="","",LOWER(TRIM(F48)&"|"&TRIM(G48)&"|"&H48)) | P48: No | Q48: Citations: 0
A49: A0048 | B49: Database | C49: OpenAlex | D49: 46287 | E49: Multiple queries (Q1-Q10) | F49: World Models for Robotic Manipulation: A Survey | G49: Fangyuan Wang; Ziyuan Wang; Guorui Pei; Mengshi Zhang; 梁燦錫; Jun Hu; Zhongxuan Li; Jinsong Wu; Ning Han; Zeqing Zhang; Jiaming Qi; Hongmin Wu; Shiyao Zhang; Pai Zheng; Jia Pan; David Navarro-Alarcon; Sichao Liu; Peng Zhou | H49: 2026 | I49: SmartBot | J49: 10.1002/smb2.70053 | K49: https://doi.org/10.1002/smb2.70053 | L49: ABSTRACT Robotic manipulation depends on the ability to anticipate how actions reshape objects, contacts, and scene geometry before execution. Learned world models provide this capability by predicting task‐relevant future evolution under robot intervention, yet the term now spans latent dynamics models, action‐conditioned video generators, three‐ and four‐dimensional scene predictors, physics‐informed simulators, and predictive modules inside vision‐language‐action systems. This breadth has fragmented the literature and obscured the design choices that matter for manipulation. We survey world models for robotic manipulation through three questions: what future representation is predicted, how prediction is connected to action, and when prediction is used in the robot‐learning pipeline. We operationally define a world model as an action‐conditioned predictive system and distinguish it from perception modules, inverse models, policies, rewards, and value functions. We then organize existing work into five representation families, develop a functional taxonomy that separates integrated prediction–action models from explicit predictive planners, and characterize infrastructure roles including synthetic experience generation, candidate filtering, search‐based evaluation, learned environments, and outcome verification. We further map these roles across pretraining, post‐training, and inference adaptation, review 38 manipulation datasets, and synthesize evaluation protocols for predictive fidelity, task performance, and simulator reliability. This survey shows that world models are evolving from task‐specific dynamics predictors into predictive infrastructure for robot learning, while exposing open challenges in contact modeling, hallucination control, action alignment, and benchmarking under closed‐loop use. | M49: article | N49: en | O49: =IF(F49="","",LOWER(TRIM(F49)&"|"&TRIM(G49)&"|"&H49)) | P49: No | Q49: Citations: 0
A50: A0049 | B50: Database | C50: OpenAlex | D50: 46287 | E50: Multiple queries (Q1-Q10) | F50: Towards Heritage World Models | G50: George Pavlidis; Vasileios Sevetlidis; Vasileios Arampatzakis | H50: 2026 | I50: Heritage | J50: 10.3390/heritage9060233 | K50: https://doi.org/10.3390/heritage9060233 | L50: Digital twins have become a central paradigm for cultural heritage documentation, monitoring, and preventive preservation. Yet, when cultural heritage systems promise prediction, simulation, intervention planning, and decision support, a more explicit account is needed of the computational commitments behind such claims. This position paper proposes the notion of the heritage world model as a conceptual and architectural abstraction that uses the semantic digital twin as its representational layer and extends it toward prediction, memory, uncertainty-aware reasoning, and intervention evaluation. We define a heritage world model as a structured, temporally updated, semantically grounded, and action-aware model of a heritage asset and its preservation environment, capable of integrating observations, estimating latent risk states, predicting plausible future trajectories, and evaluating interventions under uncertainty. The paper does not present a validated deployed system. Rather, it clarifies the architectural conditions under which a decision-support digital twin infrastructure could support the kind of world-model-like preservation system proposed here. It further argues that such a model becomes operationally meaningful only when it includes a human-supervised controller layer that maps semantic state, predicted risk trajectories, uncertainty, memory, and institutional constraints into preservation-relevant actions, alerts, monitoring adaptations, or requests for expert review. Sensor data, remote sensing, computational models, risk assessments, policies, and conservation actions are interpreted as possible observational, dynamic, and intervention layers of a heritage world model. The paper reviews adjacent work in heritage digital twins, semantic and reactive ontologies, risk-aware preservation, agentic AI, and modern AI world models, and proposes a research agenda for moving toward predictive, memory-bearing, and intervention-aware preservation intelligence. | M50: article | N50: en | O50: =IF(F50="","",LOWER(TRIM(F50)&"|"&TRIM(G50)&"|"&H50)) | P50: No | Q50: Citations: 0
A51: A0050 | B51: Database | C51: OpenAlex | D51: 46287 | E51: Multiple queries (Q1-Q10) | F51: Toward a world model for corrosion science | G51: Leonardo B. Coelho; Viacheslav Shkirskiy; N. Birbilis | H51: 2026 | I51: npj Materials Degradation | J51: 10.1038/s41529-026-00826-4 | K51: https://doi.org/10.1038/s41529-026-00826-4 | L51: Abstract Corrosion is a trajectory, not an event, yet current machine learning maps fixed inputs to outputs and cannot model reliably how a corroding interface responds to intervention. We argue that world models, deep learning frameworks that learn latent physical dynamics from observation sequences, can close this gap. A physically interpretable latent space anchored to corrosion mechanisms can enable prediction, counterfactual reasoning, and discovery. We chart a path toward realising it. | M51: article | N51: en | O51: =IF(F51="","",LOWER(TRIM(F51)&"|"&TRIM(G51)&"|"&H51)) | P51: No | Q51: Citations: 0
A52: A0051 | B52: Database | C52: OpenAlex | D52: 46287 | E52: Multiple queries (Q1-Q10) | F52: Current Trends in Artificial Intelligence Architectures: From Model Scaling to System Intelligence, Post-Transformer Hybrids and World Models | G52: Salvatore Rampone | H52: 2026 | I52: Electronics | J52: 10.3390/electronics15153254 | K52: https://doi.org/10.3390/electronics15153254 | L52: Artificial intelligence architecture is no longer adequately described by model size alone. Dense Transformers remain the reference architecture for language and multimodal reasoning, but production systems increasingly combine conditional computation, retrieval, memory, tools, verifiers, edge-cloud routing, observability and governance. This review makes three engineering claims. First, sparse Mixture-of-Experts models are currently the clearest capacity-scaling pattern, because they decouple total parameters from active per-token computation, although routing imbalance and distributed communication remain hard constraints. Second, state-space, recurrent and linear attention hybrids are best interpreted as attention-budgeting architectures: they reduce KV-cache and long-context costs, but do not yet displace dense attention in every reasoning regime. Third, JEPA-style latent world models change the learning objective from surface-token or pixel prediction to representation prediction, which is strategically important for perception and planning but still not a drop-in replacement for general language interfaces. To make the maturity claims auditable, this review uses a PRISMA-inspired search protocol, an explicit technology readiness rubric, quantitative comparison tables, hardware and memory-bandwidth analysis, deployment and reproducibility categories, and failure cases for RAG and agents. The main conclusion is that the optimal architecture is taskand constraint-dependent: small dense or hybrid models are often preferred for real-time edge inference, RAG and graph memory for changing enterprise knowledge, frontier dense or sparse models for difficult reasoning, and agentic workflows only when tool permissions, rollback, provenance and human oversight are engineered as first-class components. | M52: article | N52: en | O52: =IF(F52="","",LOWER(TRIM(F52)&"|"&TRIM(G52)&"|"&H52)) | P52: No | Q52: Citations: 0
A53: A0052 | B53: Database | C53: OpenAlex | D53: 46287 | E53: Multiple queries (Q1-Q10) | F53: Movemur: Large World Models, Newtonian Physics, and the Embodied Bottleneck of Artificial General Intelligence | G53: Enrique Díaz Cantón | H53: 2026 | I53: Journal of Climbing and Walking Robots | J53: 10.47852/bonviewjcwr620210350 | K53: https://doi.org/10.47852/bonviewjcwr620210350 | L53: Contemporary large language models achieve remarkable competence in symbolic reasoning, dialog, and the synthesis of internet-scale text and yet remain conspicuously deficient in the contact-rich, gravity-bound competence that any biological six-month-old begins to acquire while attempting to climb out of a crib. Drawing on embodied cognition, on Yann LeCun’s joint-embedding predictive architecture (JEPA) and its video extension V-JEPA 2, and on Google DeepMind’s interactive world-model line (Genie, SIMA, SIMA 2), this review argues that the principal remaining bottleneck on the path to artificial general intelligence (AGI) is not linguistic or symbolic but Newtonian: the capacity to ground perception, planning, and action within the constraints of classical mechanics as they impinge on a physical body in real time. We propose that climbing and walking robots occupy a privileged position in this research program because locomotion compresses into a single integrated task virtually every requirement for embodied intelligence under physical law while imposing failure modes that are immediate and irreversible. Building on prior surgical and grappling benchmarks, we introduce a Pauline diagnostic triad (vivimus/movemur/sumus), review recent empirical landmarks of legged-robot learning, outline a milestone ladder for locomotion-grounded embodied AGI, and frame the field’s stance toward the sim-to-real gap. The thesis is concise: until an autonomous system can climb an unfamiliar staircase, traverse rubble, and recover from a slip with adult competence, claims of general intelligence remain rhetorical. We advance this as a falsifiable hypothesis: walking and climbing are plausibly necessary, though not sufficient, conditions for it. Received: 9 May 2026 | Revised: 10 July 2026 | Accepted: 24 July 2026 Conflicts of Interest The author declares that he has no conflicts of interest to this work. Data Availability Statement Data sharing is not applicable to this article as no new data were created or analyzed in this study. Author Contribution Statement Enrique Díaz Cantón: Conceptualization, Methodology, Validation, Formal analysis, Investigation, Resources, Writing – original draft, Writing – review & editing, Visualization, Supervision, Project administration. | M53: article | O53: =IF(F53="","",LOWER(TRIM(F53)&"|"&TRIM(G53)&"|"&H53)) | P53: No | Q53: Citations: 0
A54: A0053 | B54: Database | C54: OpenAlex | D54: 46287 | E54: Multiple queries (Q1-Q10) | F54: World models for biomedicine | G54: Ayush Noori; Nic Fishman; Ada Fang; Lukas Fesser; Marinka Žitnik | H54: 2026 | I54: Cell | J54: 10.1016/j.cell.2026.08.032 | K54: https://doi.org/10.1016/j.cell.2026.08.032 | L54: Biological systems respond dynamically to changes in their environment, and predicting these responses before complex interventions are applied could change how computational models are used in biology and medicine. In artificial intelligence, world models represent the state of a system and simulate how it evolves under alternative actions. We envision extending this paradigm to biomedicine, with world models that span molecular, cellular, tissue, and clinical scales and simulate biological trajectories under alternative interventions. Building such models will require methods that combine observational data with interventional and longitudinal measurements across modalities. Biomedical world models could open new modes of inquiry by predicting how biological systems respond to novel perturbations, searching for interventions that drive them toward desired states, and planning experimental campaigns over extended time horizons. | M54: article | N54: en | O54: =IF(F54="","",LOWER(TRIM(F54)&"|"&TRIM(G54)&"|"&H54)) | P54: No | Q54: Citations: 0
A55: A0054 | B55: Database | C55: OpenAlex | D55: 46287 | E55: Multiple queries (Q1-Q10) | F55: A Comprehensive Review of Multimodal Visual Representation Learning: Tracing the Evolution from CNNs to Transformers and Beyond | G55: Dong Zhang; W. K. Wong; Ing Ming Chew | H55: 2025 | I55: International Journal of Multimedia Information Retrieval | J55: 10.1007/s13735-025-00382-8 | K55: https://doi.org/10.1007/s13735-025-00382-8 | L55: Abstract The primary goal of multimodal visual representation learning is to generate implicit information that effectively represents multimodal information by exploring the commonalities and characteristics between different modalities. This research report will discuss currently widely used advanced methods in the field of multimodal visual representation learning. This article will discuss these methods in the following order, culminating in multimodal visual learning: (1) pre-trained visual representation learning, (2) generative visual representation learning, (3) contrastive multimodal visual representation learning, and (4) image-text multimodal visual representation learning methods. Each element provides useful clues that ultimately lead to multimodal visual learning. Pre-trained visual representation learning refers to the application of supervised pre-training models in visual representation learning, while generative visual representation learning uses generative models to learn feature representations that can integrate multimodal information. Contrastive multimodal visual representation learning uses contrastive learning methods to compare similar and dissimilar sample pairs, learning feature representations in a self-supervised manner. Image-text multimodal visual representation learning methods, on the other hand, attempt to enhance the capabilities of visual representation learning by fusing visual information (such as images) with textual information. This review report will explain the above research background, the classification of different research methods, commonly used evaluation methods , and future development trends. | M55: article | N55: en | O55: =IF(F55="","",LOWER(TRIM(F55)&"|"&TRIM(G55)&"|"&H55)) | P55: No | Q55: Citations: 2
A56: A0055 | B56: Database | C56: OpenAlex | D56: 46287 | E56: Multiple queries (Q1-Q10) | F56: The Cost of Dreaming: A Survey of Computational Constraints in Generative and Latent World Models | G56: Hasaan Ahmad; Haixia Liu | H56: 2026 | I56: IEEE Computational Intelligence Magazine | J56: 10.1109/mci.2026.3713292 | K56: https://doi.org/10.1109/mci.2026.3713292 | L56: Recent generative architectures such as Genie3 achieve 24 Frames Per Second at 720p resolution when served from Google Tensor Processing Unit clusters, requiring cloud deployment that introduces latency challenging real-time control in safety-critical robotics. Despite rapid architectural progress, computational efficiency metrics are inconsistently reported across the field; inference latency, parameter counts, and hardware requirements are disclosed selectively, while memory footprint (reported for only 40% of surveyed models) and power consumption (0% of surveyed models) remain largely unmeasured. This reporting gap obscures the efficiency-accuracy frontier and prevents practitioners from making informed deployment decisions. This paper surveys 15 representative world models spanning generative (pixel-space) and latent (joint-embedding) architec-tures published 2023-2025. We organize these models into a two-tier taxonomy: Tier 1 baseline paradigms (generative vs. latent) and Tier 2 optimization strategies (compression, acceleration, edge deployment). We establish an efficiency frontier spanning five orders of magnitude: from ultra-fast action selection (Deep AIF: 2.37 ms) to multi-second generative models (Cosmos: 383 s per sequence). Our analysis reveals efficiency-optimized models achieving 4.4-75× speedups through latent-space prediction, token compression, and architectural parallelization. We find that high-dimensional sequential operations inside the synchronous control loop appear to be a key bottleneck within the surveyed models, potentially limiting real-time performance. We outline three research priorities toward sub-100 milliseconds on-device models: hierarchical "fast-slow" architectures, dynamics-aware quantization, and standardized efficiency reporting. Our systematic comparison provides actionable deployment guidelines for robotics practitioners navigating the efficiency-expressiveness trade-off. | M56: article | N56: en | O56: =IF(F56="","",LOWER(TRIM(F56)&"|"&TRIM(G56)&"|"&H56)) | P56: No | Q56: Citations: 0
A57: A0056 | B57: Database | C57: OpenAlex | D57: 46287 | E57: Multiple queries (Q1-Q10) | F57: Modern Prometheus: tracing the ill-defined path to AGI | G57: Matthew Landers | H57: 2025 | I57: AI & Society | J57: 10.1007/s00146-025-02363-1 | K57: https://doi.org/10.1007/s00146-025-02363-1 | L57: Abstract This article traces the conceptual lineage of AGI through three influential paradigms: strong AI, human-level AI, and AGI—highlighting the philosophical and operational tensions shaping contemporary debates. The article examines emerging reorientations toward operational benchmarks that decouple artificial intelligence from human-like cognition. It proposes a novel taxonomy to evaluate divergent developmental trajectories—Promethean and Noctuidean orientations—and argues that anthropocentric biases may limit recognition of diverse intelligences and amplify risks in AI deployment. Through careful analysis of historical contexts, philosophical arguments, recent technological advances, and emerging legal disputes, this article underscores an urgent need to clarify definitions and goals in the race to AGI. | M57: article | N57: en | O57: =IF(F57="","",LOWER(TRIM(F57)&"|"&TRIM(G57)&"|"&H57)) | P57: No | Q57: Citations: 3
A58: A0057 | B58: Database | C58: OpenAlex | D58: 46287 | E58: Multiple queries (Q1-Q10) | F58: ORION: A Hierarchical Surgical World Model for Real-Time, Multi-Agent Operating-Room Intelligence | G58: Dev Mehta; R. T. Charulatha | H58: 2026 | I58: Journal of Ubiquitous Computing and Communication Technologies | J58: 10.36548/jucct.2026.3.008 | K58: https://doi.org/10.36548/jucct.2026.3.008 | L58: Modern operating suites generate dense, heterogeneous data streams endoscopic video, multi-parameter vitals, anesthesia registers, device telemetry, intraoperative imaging, and robotic kinematics yet the overwhelming majority of these signals are discarded, with the complete clinical reality of a procedure routinely collapsed into a single postoperative note. This documentation bottleneck loses roughly ninety-nine percent of the granular information produced during surgery, preventing systematic audit, objective skill assessment, and longitudinal research. We present ORION (Operating Room Intelligence and Optimization Network), an AI-native platform that transforms multi-sensory input into a continuously updated digital twin of the patient and operating environment. ORION is organised as a twelve-layer Hierarchical Surgical World Model (HSWM) spanning real-time perception, relational scene-graph construction, a Gaussian-splatting digital twin, temporal workflow modelling, predictive risk forecasting, knowledge grounding, and multi-agent clinical reasoning. A generative component, SurgWorld, mitigates kinematic-data scarcity by synthesising physically plausible surgical video and recovering pseudo-kinematics through an inverse-dynamics model. Because ORION is presented as a proposed architectural framework, the reported Cholec80 and AutoLaparo figures up to 94.6% and 89.5% accuracy at 238.7 FPS for the underlying state-space model are drawn from the constituent methods' published evaluations, not a new experiment; prospective validation of the integrated system is future work. The reporting layer is designed to compress postoperative documentation to under thirty seconds. We further describe the low-latency execution architecture (NVIDIA Holoscan and Triton) required to stay below the 50 ms perceptual threshold, and map the platform onto India's CDSCO Software-as-a-Medical-Device regulatory pathway | M58: article | O58: =IF(F58="","",LOWER(TRIM(F58)&"|"&TRIM(G58)&"|"&H58)) | P58: No | Q58: Citations: 0
A59: A0058 | B59: Database | C59: OpenAlex | D59: 46287 | E59: Multiple queries (Q1-Q10) | F59: Diffusion Models: A Comprehensive Survey of Methods and Applications | G59: L. Yang; Zhilong Zhang; Yang Song; Shenda Hong; Runsheng Xu; Yue Zhao; Wentao Zhang; Bin Cui; Ming–Hsuan Yang | H59: 2023 | I59: ACM Computing Surveys | J59: 10.1145/3626235 | K59: https://doi.org/10.1145/3626235 | L59: Diffusion models have emerged as a powerful new family of deep generative models with record-breaking performance in many applications, including image synthesis, video generation, and molecule design. In this survey, we provide an overview of the rapidly expanding body of work on diffusion models, categorizing the research into three key areas: efficient sampling, improved likelihood estimation, and handling data with special structures. We also discuss the potential for combining diffusion models with other generative models for enhanced results. We further review the wide-ranging applications of diffusion models in fields spanning from computer vision, natural language processing, temporal data modeling, to interdisciplinary applications in other scientific disciplines. This survey aims to provide a contextualized, in-depth look at the state of diffusion models, identifying the key areas of focus and pointing to potential areas for further exploration. Github: https://github.com/YangLing0818/Diffusion-Models-Papers-Survey-Taxonomy | M59: article | N59: en | O59: =IF(F59="","",LOWER(TRIM(F59)&"|"&TRIM(G59)&"|"&H59)) | P59: No | Q59: Citations: 1563
A60: A0059 | B60: Database | C60: OpenAlex | D60: 46287 | E60: Multiple queries (Q1-Q10) | F60: Generative AI | G60: Stefan Feuerriegel; Jochen Hartmann; Christian Janiesch; Patrick Zschech | H60: 2023 | I60: Business & Information Systems Engineering | J60: 10.1007/s12599-023-00834-7 | K60: https://doi.org/10.1007/s12599-023-00834-7 | L60: Tom Freston is credited with saying “Innovation is taking two things that exist and putting them together in a new way”. For a long time in history, it has been the prevailing assumption that artistic, creative tasks such as writing poems, creating software, designing fashion, and composing songs could only be performed by humans. This assumption has changed drastically with recent advances in artificial intelligence (AI) that can generate new content in ways that cannot be distinguished anymore from human craftsmanship. | M60: article | N60: en | O60: =IF(F60="","",LOWER(TRIM(F60)&"|"&TRIM(G60)&"|"&H60)) | P60: No | Q60: Citations: 1373
A61: A0060 | B61: Database | C61: OpenAlex | D61: 46287 | E61: Multiple queries (Q1-Q10) | F61: Opinion Paper: “So what if ChatGPT wrote it?” Multidisciplinary perspectives on opportunities, challenges and implications of generative conversational AI for research, practice and policy | G61: Yogesh K. Dwivedi; Nir Kshetri; Laurie Hughes; Emma Slade; Anand Jeyaraj; Arpan Kumar Kar; Abdullah M. Baabdullah; Alex Koohang; Vishnupriya Raghavan; Manju Ahuja; Hanaa Albanna; Mousa Ahmad Albashrawi; Adil S. Al-Busaidi; Janarthanan Balakrishnan; Yves Barlette; Sriparna Basu; Indranil Bose; Laurence Brooks; Dimitrios Buhalis; Lemuria Carter; Soumyadeb Chowdhury; Tom Crick; Scott W. Cunningham; Gareth H. Davies; Robert M. Davison; Rahul Dé; Denis Dennehy; Yanqing Duan; Rameshwar Dubey; Rohita Dwivedi; John S. Edwards; Carlos Flavián; Robin Gauld; Varun Grover; Mei‐Chih Hu; Marijn Janssen; Paul Jones; Iris Junglas; Sangeeta Khorana; Sascha Kraus; Kai R. Larsen; Paul Latreille; Sven Laumer; Tegwen Malik; Abbas Mardani; Marcello Mariani; Sunil Mithas; Emmanuel Mogaji; Jeretta Horn Nord; Siobhán O’Connor; Fevzi Okumus; Margherita Pagani; Neeraj Pandey; Savvas Papagiannidis; Ilias O. Pappas; Nishith Pathak; Jan Pries‐Heje; Ramakrishnan Raman; Nripendra P. Rana; Sven‐Volker Rehm; Samuel Ribeiro‐Navarrete; Alexander Richter; Frantz Rowe; Suprateek Sarker; Bernd Carsten Stahl; Manoj Tiwari; Wil van der Aalst; Viswanath Venkatesh; Giampaolo Viglia; Michael Wade; Paul Walton; Jochen Wirtz; Ryan Wright | H61: 2023 | I61: International Journal of Information Management | J61: 10.1016/j.ijinfomgt.2023.102642 | K61: https://doi.org/10.1016/j.ijinfomgt.2023.102642 | L61: Transformative artificially intelligent tools, such as ChatGPT, designed to generate sophisticated text indistinguishable from that produced by a human, are applicable across a wide range of contexts. The technology presents opportunities as well as, often ethical and legal, challenges, and has the potential for both positive and negative impacts for organisations, society, and individuals. Offering multi-disciplinary insight into some of these, this article brings together 43 contributions from experts in fields such as computer science, marketing, information systems, education, policy, hospitality and tourism, management, publishing, and nursing. The contributors acknowledge ChatGPT’s capabilities to enhance productivity and suggest that it is likely to offer significant gains in the banking, hospitality and tourism, and information technology industries, and enhance business activities, such as management and marketing. Nevertheless, they also consider its limitations, disruptions to practices, threats to privacy and security, and consequences of biases, misuse, and misinformation. However, opinion is split on whether ChatGPT’s use should be restricted or legislated. Drawing on these contributions, the article identifies questions requiring further research across three thematic areas: knowledge, transparency, and ethics; digital transformation of organisations and societies; and teaching, learning, and scholarly research. The avenues for further research include: identifying skills, resources, and capabilities needed to handle generative AI; examining biases of generative AI attributable to training datasets and processes; exploring business and societal contexts best suited for generative AI implementation; determining optimal combinations of human and generative AI for various tasks; identifying ways to assess accuracy of text produced by generative AI; and uncovering the ethical and legal issues in using generative AI across different contexts. | M61: article | N61: en | O61: =IF(F61="","",LOWER(TRIM(F61)&"|"&TRIM(G61)&"|"&H61)) | P61: No | Q61: Citations: 4337
A62: A0061 | B62: Database | C62: OpenAlex | D62: 46287 | E62: Multiple queries (Q1-Q10) | F62: Deep Generative Modelling: A Comparative Review of VAEs, GANs, Normalizing Flows, Energy-Based and Autoregressive Models | G62: Leach, Adam | H62: 2021 | I62: Durham Research Online (Durham University) | J62: 10.1109/tpami.2021.3116668 | K62: https://doi.org/10.1109/tpami.2021.3116668 | L62: Deep generative models are a class of techniques that train deep neural networks to model the distribution of training samples. Research has fragmented into various interconnected approaches, each of which make trade-offs including run-time, diversity, and architectural restrictions. In particular, this compendium covers energy-based models, variational autoencoders, generative adversarial networks, autoregressive models, normalizing flows, in addition to numerous hybrid approaches. These techniques are compared and contrasted, explaining the premises behind each and how they are interrelated, while reviewing current state-of-the-art advances and implementations. | M62: article | N62: en | O62: =IF(F62="","",LOWER(TRIM(F62)&"|"&TRIM(G62)&"|"&H62)) | P62: No | Q62: Citations: 683
A63: A0062 | B63: Database | C63: OpenAlex | D63: 46287 | E63: Multiple queries (Q1-Q10) | F63: Generative artificial intelligence | G63: Leonardo Banh; Gero Strobel | H63: 2023 | I63: Electronic Markets | J63: 10.1007/s12525-023-00680-1 | K63: https://doi.org/10.1007/s12525-023-00680-1 | L63: Abstract Recent developments in the field of artificial intelligence (AI) have enabled new paradigms of machine processing, shifting from data-driven, discriminative AI tasks toward sophisticated, creative tasks through generative AI. Leveraging deep generative models, generative AI is capable of producing novel and realistic content across a broad spectrum (e.g., texts, images, or programming code) for various domains based on basic user prompts. In this article, we offer a comprehensive overview of the fundamentals of generative AI with its underpinning concepts and prospects. We provide a conceptual introduction to relevant terms and techniques, outline the inherent properties that constitute generative AI, and elaborate on the potentials and challenges. We underline the necessity for researchers and practitioners to comprehend the distinctive characteristics of generative artificial intelligence in order to harness its potential while mitigating its risks and to contribute to a principal understanding. | M63: article | N63: en | O63: =IF(F63="","",LOWER(TRIM(F63)&"|"&TRIM(G63)&"|"&H63)) | P63: No | Q63: Citations: 562
A64: A0063 | B64: Database | C64: OpenAlex | D64: 46287 | E64: Multiple queries (Q1-Q10) | F64: The Power of Generative AI: A Review of Requirements, Models, Input–Output Formats, Evaluation Metrics, and Challenges | G64: Ajay Bandi; Pydi Venkata Satya Ramesh Adapa; Yudu Eswar Vinay Pratap Kumar Kuchi | H64: 2023 | I64: Future Internet | J64: 10.3390/fi15080260 | K64: https://doi.org/10.3390/fi15080260 | L64: Generative artificial intelligence (AI) has emerged as a powerful technology with numerous applications in various domains. There is a need to identify the requirements and evaluation metrics for generative AI models designed for specific tasks. The purpose of the research aims to investigate the fundamental aspects of generative AI systems, including their requirements, models, input–output formats, and evaluation metrics. The study addresses key research questions and presents comprehensive insights to guide researchers, developers, and practitioners in the field. Firstly, the requirements necessary for implementing generative AI systems are examined and categorized into three distinct categories: hardware, software, and user experience. Furthermore, the study explores the different types of generative AI models described in the literature by presenting a taxonomy based on architectural characteristics, such as variational autoencoders (VAEs), generative adversarial networks (GANs), diffusion models, transformers, language models, normalizing flow models, and hybrid models. A comprehensive classification of input and output formats used in generative AI systems is also provided. Moreover, the research proposes a classification system based on output types and discusses commonly used evaluation metrics in generative AI. The findings contribute to advancements in the field, enabling researchers, developers, and practitioners to effectively implement and evaluate generative AI models for various applications. The significance of the research lies in understanding that generative AI system requirements are crucial for effective planning, design, and optimal performance. A taxonomy of models aids in selecting suitable options and driving advancements. Classifying input–output formats enables leveraging diverse formats for customized systems, while evaluation metrics establish standardized methods to assess model quality and performance. | M64: article | N64: en | O64: =IF(F64="","",LOWER(TRIM(F64)&"|"&TRIM(G64)&"|"&H64)) | P64: No | Q64: Citations: 630
A65: A0064 | B65: Database | C65: OpenAlex | D65: 46287 | E65: Multiple queries (Q1-Q10) | F65: The GenAI is out of the bottle: generative artificial intelligence from a business model innovation perspective | G65: Dominik K. Kanbach; Louisa Heiduk; Georg Blueher; Maximilian Schreiter; Alexander Lahmann | H65: 2023 | I65: Review of Managerial Science | J65: 10.1007/s11846-023-00696-z | K65: https://doi.org/10.1007/s11846-023-00696-z | L65: Abstract The introduction of ChatGPT in November 2022 by OpenAI has stimulated substantial discourse on the implementation of artificial intelligence (AI) in various domains such as academia, business, and society at large. Although AI has been utilized in numerous areas for several years, the emergence of generative AI (GAI) applications such as ChatGPT, Jasper, or DALL-E are considered a breakthrough for the acceleration of AI technology due to their ease of use, intuitive interface, and performance. With GAI, it is possible to create a variety of content such as texts, images, audio, code, and even videos. This creates a variety of implications for businesses requiring a deeper examination, including an influence on business model innovation (BMI). Therefore, this study provides a BMI perspective on GAI with two primary contributions: (1) The development of six comprehensive propositions outlining the impact of GAI on businesses, and (2) the discussion of three industry examples, specifically software engineering, healthcare, and financial services. This study employs a qualitative content analysis using a scoping review methodology, drawing from a wide-ranging sample of 513 data points. These include academic publications, company reports, and public information such as press releases, news articles, interviews, and podcasts. The study thus contributes to the growing academic discourse in management research concerning AI's potential impact and offers practical insights into how to utilize this technology to develop new or improve existing business models. | M65: article | N65: en | O65: =IF(F65="","",LOWER(TRIM(F65)&"|"&TRIM(G65)&"|"&H65)) | P65: No | Q65: Citations: 459
A66: A0065 | B66: Database | C66: OpenAlex | D66: 46287 | E66: Multiple queries (Q1-Q10) | F66: Parameterized quantum circuits as machine learning models | G66: Marcello Benedetti; Erika Lloyd; Stefan Sack; Mattia Fiorentini | H66: 2019 | I66: Quantum Science and Technology | J66: 10.1088/2058-9565/ab4eb5 | K66: https://doi.org/10.1088/2058-9565/ab4eb5 | L66: Abstract Hybrid quantum–classical systems make it possible to utilize existing quantum computers to their fullest extent. Within this framework, parameterized quantum circuits can be regarded as machine learning models with remarkable expressive power. This Review presents the components of these models and discusses their application to a variety of data-driven tasks, such as supervised learning and generative modeling. With an increasing number of experimental demonstrations carried out on actual quantum hardware and with software being actively developed, this rapidly growing field is poised to have a broad spectrum of real-world applications. | M66: article | N66: en | O66: =IF(F66="","",LOWER(TRIM(F66)&"|"&TRIM(G66)&"|"&H66)) | P66: No | Q66: Citations: 1129
A67: A0066 | B67: Database | C67: OpenAlex | D67: 46287 | E67: Multiple queries (Q1-Q10) | F67: Promises and challenges of generative artificial intelligence for human learning | G67: Lixiang Yan; Samuel Greiff; Ziwen Teuber; Dragan Gašević | H67: 2024 | I67: Nature Human Behaviour | J67: 10.1038/s41562-024-02004-5 | K67: https://doi.org/10.1038/s41562-024-02004-5 | M67: article | N67: en | O67: =IF(F67="","",LOWER(TRIM(F67)&"|"&TRIM(G67)&"|"&H67)) | P67: No | Q67: Citations: 453
A68: A0067 | B68: Database | C68: OpenAlex | D68: 46287 | E68: Multiple queries (Q1-Q10) | F68: Large language models for generative information extraction: a survey | G68: Derong Xu; Wei Chen; Wenjun Peng; Chao Zhang; Tong Xu; Xiangyu Zhao; Xian Wu; Yefeng Zheng; Yan Wang; Enhong Chen | H68: 2024 | I68: Frontiers of Computer Science | J68: 10.1007/s11704-024-40555-y | K68: https://doi.org/10.1007/s11704-024-40555-y | L68: Abstract Information Extraction (IE) aims to extract structural knowledge from plain natural language texts. Recently, generative Large Language Models (LLMs) have demonstrated remarkable capabilities in text understanding and generation. As a result, numerous works have been proposed to integrate LLMs for IE tasks based on a generative paradigm. To conduct a comprehensive systematic review and exploration of LLM efforts for IE tasks, in this study, we survey the most recent advancements in this field. We first present an extensive overview by categorizing these works in terms of various IE subtasks and techniques, and then we empirically analyze the most advanced methods and discover the emerging trend of IE tasks with LLMs. Based on a thorough review conducted, we identify several insights in technique and promising research directions that deserve further exploration in future studies. We maintain a public repository and consistently update related works and resources on GitHub (LLM4IE repository). | M68: article | N68: en | O68: =IF(F68="","",LOWER(TRIM(F68)&"|"&TRIM(G68)&"|"&H68)) | P68: No | Q68: Citations: 279
A69: A0068 | B69: Database | C69: OpenAlex | D69: 46287 | E69: Multiple queries (Q1-Q10) | F69: Generative Artificial Intelligence: Trends and Prospects | G69: Mladjan Jovanovic; Mark Campbell | H69: 2022 | I69: Computer | J69: 10.1109/mc.2022.3192720 | K69: https://doi.org/10.1109/mc.2022.3192720 | L69: Generative artificial intelligence can make powerful artifacts when used at scale, but developing trust in these artifacts and controlling their creation are essential for user adoption. | M69: article | N69: en | O69: =IF(F69="","",LOWER(TRIM(F69)&"|"&TRIM(G69)&"|"&H69)) | P69: No | Q69: Citations: 354
A70: A0069 | B70: Database | C70: OpenAlex | D70: 46287 | E70: Multiple queries (Q1-Q10) | F70: Deepfakes and Disinformation: Exploring the Impact of Synthetic Political Video on Deception, Uncertainty, and Trust in News | G70: Cristian Vaccari; Andrew Chadwick | H70: 2020 | I70: Social Media + Society | J70: 10.1177/2056305120903408 | K70: https://doi.org/10.1177/2056305120903408 | L70: Artificial Intelligence (AI) now enables the mass creation of what have become known as “deepfakes”: synthetic videos that closely resemble real videos. Integrating theories about the power of visual communication and the role played by uncertainty in undermining trust in public discourse, we explain the likely contribution of deepfakes to online disinformation. Administering novel experimental treatments to a large representative sample of the United Kingdom population allowed us to compare people’s evaluations of deepfakes. We find that people are more likely to feel uncertain than to be misled by deepfakes, but this resulting uncertainty, in turn, reduces trust in news on social media. We conclude that deepfakes may contribute toward generalized indeterminacy and cynicism, further intensifying recent challenges to online civic culture in democratic societies. | M70: article | N70: en | O70: =IF(F70="","",LOWER(TRIM(F70)&"|"&TRIM(G70)&"|"&H70)) | P70: No | Q70: Citations: 940
A71: A0070 | B71: Database | C71: OpenAlex | D71: 46287 | E71: Multiple queries (Q1-Q10) | F71: Beyond Reality: The Pivotal Role of Generative AI in the Metaverse | G71: Vinay Chamola; Gaurang Bansal; Tridib Kumar Das; Vikas Hassija; Siva Sai; Jiacheng Wang; Sherali Zeadally; Amir Hussain; F. Richard Yu; Mohsen Guizani; Dusit Niyato | H71: 2024 | I71: IEEE Internet of Things Magazine | J71: 10.1109/iotm.001.2300174 | K71: https://doi.org/10.1109/iotm.001.2300174 | L71: The Metaverse, an interconnected network of immersive digital realms, is poised to reshape the future by seamlessly merging physical reality with virtual environments. Its potential to revolutionize diverse aspects of human existence, from entertainment to commerce, underscores its significance. At the heart of this transformation lies Generative AI, a branch of artificial intelligence focused on creating novel content. Generative AI serves as a catalyst, propelling the Metaverse's evolution by enhancing it with immersive experiences. The Metaverse is comprised of three pivotal domains, namely, text, visual, and audio. The Metaverse's fabric intertwines with Generative AI models, ushering in innovative interactions. Within Visual, the triad of image, video, and 3D Object generation sets the stage for engaging virtual landscapes. Key to this evolution is five generative models: Transformers, Diffusion, Autoencoders, Autoregressive, and Generative Adversarial Networks (GANs). These models empower the Metaverse, enhancing it with dynamic and diverse content. Notably, technologies like BARD, Point-E, Stable Diffusion, DALL-E, GPT, and AIVA, among others, wield these models to enrich the Metaverse across domains. By discussing the technical issues and real-world applications, this study reveals the intricate tapestry of AI's role in the Metaverse. Anchoring these insights is a case study illuminating Stable Diffusion's role in metamorphosing the virtual realm. Collectively, this exploration illuminates the symbiotic relationship between Generative AI and the Metaverse, foreshadowing a future where immersive, interactive, and personalized experiences blackefine human engagement with digital landscapes. | M71: article | N71: en | O71: =IF(F71="","",LOWER(TRIM(F71)&"|"&TRIM(G71)&"|"&H71)) | P71: No | Q71: Citations: 86
A72: A0071 | B72: Database | C72: OpenAlex | D72: 46287 | E72: Multiple queries (Q1-Q10) | F72: Leveraging Generative AI and Large Language Models: A Comprehensive Roadmap for Healthcare Integration | G72: Ping Yu; Hua Xu; Xia Hu; Chao Deng | H72: 2023 | I72: Healthcare | J72: 10.3390/healthcare11202776 | K72: https://doi.org/10.3390/healthcare11202776 | L72: Generative artificial intelligence (AI) and large language models (LLMs), exemplified by ChatGPT, are promising for revolutionizing data and information management in healthcare and medicine. However, there is scant literature guiding their integration for non-AI professionals. This study conducts a scoping literature review to address the critical need for guidance on integrating generative AI and LLMs into healthcare and medical practices. It elucidates the distinct mechanisms underpinning these technologies, such as Reinforcement Learning from Human Feedback (RLFH), including few-shot learning and chain-of-thought reasoning, which differentiates them from traditional, rule-based AI systems. It requires an inclusive, collaborative co-design process that engages all pertinent stakeholders, including clinicians and consumers, to achieve these benefits. Although global research is examining both opportunities and challenges, including ethical and legal dimensions, LLMs offer promising advancements in healthcare by enhancing data management, information retrieval, and decision-making processes. Continued innovation in data acquisition, model fine-tuning, prompt strategy development, evaluation, and system implementation is imperative for realizing the full potential of these technologies. Organizations should proactively engage with these technologies to improve healthcare quality, safety, and efficiency, adhering to ethical and legal guidelines for responsible application. | M72: article | N72: en | O72: =IF(F72="","",LOWER(TRIM(F72)&"|"&TRIM(G72)&"|"&H72)) | P72: No | Q72: Citations: 259
A73: A0072 | B73: Database | C73: OpenAlex | D73: 46287 | E73: Multiple queries (Q1-Q10) | F73: Opportunities and challenges of diffusion models for generative AI | G73: Minshuo Chen; Mei Song; Jianqing Fan; Mengdi Wang | H73: 2024 | I73: National Science Review | J73: 10.1093/nsr/nwae348 | K73: https://doi.org/10.1093/nsr/nwae348 | L73: Diffusion models, a powerful and universal generative artificial intelligence technology, have achieved tremendous success and opened up new possibilities in diverse applications. In these applications, diffusion models provide flexible high-dimensional data modeling, and act as a sampler for generating new samples under active control towards task-desired properties. Despite the significant empirical success, theoretical underpinnings of diffusion models are very limited, potentially slowing down principled methodological innovations for further harnessing and improving diffusion models. In this paper, we review emerging applications of diffusion models to highlight their sample generation capabilities under various control goals. At the same time, we dive into the unique working flow of diffusion models through the lens of stochastic processes. We identify theoretical challenges in analyzing diffusion models, owing to their complicated training procedure and interaction with the underlying data distribution. To address these challenges, we overview several promising advances, demonstrating diffusion models as an efficient distribution learner and a sampler. Furthermore, we introduce a new avenue in high-dimensional structured optimization through diffusion models, where searching for solutions is reformulated as a conditional sampling problem and solved by diffusion models. Lastly, we discuss future directions about diffusion models. The purpose of this paper is to provide a well-rounded exposure for stimulating forward-looking theories and methods of diffusion models. | M73: article | N73: en | O73: =IF(F73="","",LOWER(TRIM(F73)&"|"&TRIM(G73)&"|"&H73)) | P73: No | Q73: Citations: 72
A74: A0073 | B74: Database | C74: OpenAlex | D74: 46287 | E74: Multiple queries (Q1-Q10) | F74: Generative AI for Transformative Healthcare: A Comprehensive Study of Emerging Models, Applications, Case Studies, and Limitations | G74: Siva Sai; Aanchal Gaur; R Vijay Sai; Vinay Chamola; Mohsen Guizani; Joel J. P. C. Rodrigues | H74: 2024 | I74: IEEE Access | J74: 10.1109/access.2024.3367715 | K74: https://doi.org/10.1109/access.2024.3367715 | L74: Generative artificial intelligence (GAI) can be broadly described as an artificial intelligence system capable of generating images, text, and other media types with human prompts. GAI models like ChatGPT, DALL-E, and Bard have recently caught the attention of industry and academia equally. GAI applications span various industries like art, gaming, fashion, and healthcare. In healthcare, GAI shows promise in medical research, diagnosis, treatment, and patient care and is already making strides in real-world deployments. There has yet to be any detailed study concerning the applications and scope of GAI in healthcare. Addressing this research gap, we explore several applications, real-world scenarios, and limitations of GAI in healthcare. We examine how GAI models like ChatGPT and DALL-E can be leveraged to aid in the applications of medical imaging, drug discovery, personalized patient treatment, medical simulation and training, clinical trial optimization, mental health support, healthcare operations and research, medical chatbots, human movement simulation, and a few more applications. Along with applications, we cover four real-world healthcare scenarios that employ GAI: visual snow syndrome diagnosis, molecular drug optimization, medical education, and dentistry. We also provide an elaborate discussion on seven healthcare-customized LLMs like Med-PaLM, BioGPT, DeepHealth, etc.,Since GAI is still evolving, it poses challenges like the lack of professional expertise in decision making, risk of patient data privacy, issues in integrating with existing healthcare systems, and the problem of data bias which are elaborated on in this work along with several other challenges. We also put forward multiple directions for future research in GAI for healthcare. | M74: article | N74: en | O74: =IF(F74="","",LOWER(TRIM(F74)&"|"&TRIM(G74)&"|"&H74)) | P74: No | Q74: Citations: 249
A75: A0074 | B75: Database | C75: OpenAlex | D75: 46287 | E75: Multiple queries (Q1-Q10) | F75: Generative artificial intelligence in innovation management: A preview of future research developments | G75: Marcello M. Mariani; Yogesh K. Dwivedi | H75: 2024 | I75: Journal of Business Research | J75: 10.1016/j.jbusres.2024.114542 | K75: https://doi.org/10.1016/j.jbusres.2024.114542 | L75: This study outlines the future research opportunities related to Generative Artificial Intelligence (GenAI) in innovation management. To this end, it combines a review of the academic literature with the results of a Delphi study involving leading innovation management scholars. Ten major research themes emerged that can guide future research developments at the intersection of GenAI and innovation management: 1) Gen AI and innovation types; 2) GenAI, dominant designs and technology evolution; 3) Scientific and artistic creativity and GenAI-enabled innovations; 4) GenAI-enabled innovations and intellectual property; 5) GenAI and new product development; 6) Multimodal/unimodal GenAI and innovation outcomes; 7) GenAI, agency and ecosystems; 8) Policymakers, lawmakers and anti-trust authorities in the regulation of GenAI-enabled innovation; 9) Misuse and unethical use of GenAI leading to biased innovation; and 10) Organizational design and boundaries for GenAI-enabled innovation. The paper concludes by discussing how these themes can inform theoretical development in innovation management studies. | M75: article | N75: en | O75: =IF(F75="","",LOWER(TRIM(F75)&"|"&TRIM(G75)&"|"&H75)) | P75: No | Q75: Citations: 397
A76: A0075 | B76: Database | C76: OpenAlex | D76: 46287 | E76: Multiple queries (Q1-Q10) | F76: Can Generative AI improve social science? | G76: Christopher A. Bail | H76: 2024 | I76: Proceedings of the National Academy of Sciences | J76: 10.1073/pnas.2314021121 | K76: https://doi.org/10.1073/pnas.2314021121 | L76: Generative AI that can produce realistic text, images, and other human-like outputs is currently transforming many different industries. Yet it is not yet known how such tools might influence social science research. I argue Generative AI has the potential to improve survey research, online experiments, automated content analyses, agent-based models, and other techniques commonly used to study human behavior. In the second section of this article, I discuss the many limitations of Generative. I examine how bias in the data used to train these tools can negatively impact social science research-as well as a range of other challenges related to ethics, replication, environmental impact, and the proliferation of low-quality research. I conclude by arguing that social scientists can address many of these limitations by creating open-source infrastructure for research on human behavior. Such infrastructure is not only necessary to ensure broad access to high-quality research tools, I argue, but also because the progress of AI will require deeper understanding of the social forces that guide human behavior. | M76: article | N76: en | O76: =IF(F76="","",LOWER(TRIM(F76)&"|"&TRIM(G76)&"|"&H76)) | P76: No | Q76: Citations: 293
A77: A0076 | B77: Database | C77: OpenAlex | D77: 46287 | E77: Multiple queries (Q1-Q10) | F77: Generative AI in higher education: A global perspective of institutional adoption policies and guidelines | G77: Yueqiao Jin; Lixiang Yan; Vanessa Echeverría; Dragan Gašević; Roberto Martínez‐Maldonado | H77: 2024 | I77: Computers and Education Artificial Intelligence | J77: 10.1016/j.caeai.2024.100348 | K77: https://doi.org/10.1016/j.caeai.2024.100348 | L77: Integrating generative AI (GAI) into higher education is crucial for preparing a future generation of GAI-literate students. However, a comprehensive understanding of global institutional adoption policies remains absent, with most prior studies focusing on the Global North and lacking a theoretical lens. This study utilizes the Diffusion of Innovations Theory to examine GAI adoption strategies in higher education across 40 universities from six global regions. It explores the characteristics of GAI innovation, including compatibility, trialability, and observability, and analyses the communication channels and roles and responsibilities outlined in university policies and guidelines. The findings reveal that universities are proactively addressing GAI integration by emphasising academic integrity, enhancing teaching and learning practices, and promoting equity. Key policy measures include the development of guidelines for ethical GAI use, the design of authentic assessments to mitigate misuse, and the provision of training programs for faculty and students to foster GAI literacy. Despite these efforts, gaps remain in comprehensive policy frameworks, particularly in addressing data privacy concerns and ensuring equitable access to GAI tools. The study underscores the importance of clear communication channels, stakeholder collaboration, and ongoing evaluation to support effective GAI adoption. These insights provide actionable insights for policymakers to craft inclusive, transparent, and adaptive strategies for integrating GAI into higher education. | M77: article | N77: en | O77: =IF(F77="","",LOWER(TRIM(F77)&"|"&TRIM(G77)&"|"&H77)) | P77: No | Q77: Citations: 356
A78: A0077 | B78: Database | C78: OpenAlex | D78: 46287 | E78: Multiple queries (Q1-Q10) | F78: DiffuRec: A Diffusion Model for Sequential Recommendation | G78: Zihao Li; Aixin Sun; Chenliang Li | H78: 2023 | I78: ACM Transactions on Information Systems | J78: 10.1145/3631116 | K78: https://doi.org/10.1145/3631116 | L78: Mainstream solutions to sequential recommendation represent items with fixed vectors. These vectors have limited capability in capturing items’ latent aspects and users’ diverse preferences. As a new generative paradigm, diffusion models have achieved excellent performance in areas like computer vision and natural language processing. To our understanding, its unique merit in representation generation well fits the problem setting of sequential recommendation. In this article, we make the very first attempt to adapt the diffusion model to sequential recommendation and propose DiffuRec for item representation construction and uncertainty injection. Rather than modeling item representations as fixed vectors, we represent them as distributions in DiffuRec , which reflect a user’s multiple interests and an item’s various aspects adaptively. In the diffusion phase, DiffuRec corrupts the target item embedding into a Gaussian distribution via noise adding, which is further applied for sequential item distribution representation generation and uncertainty injection. Afterward, the item representation is fed into an approximator for target item representation reconstruction. In the reverse phase, based on a user’s historical interaction behaviors, we reverse a Gaussian noise into the target item representation, then apply a rounding operation for target item prediction. Experiments over four datasets show that DiffuRec outperforms strong baselines by a large margin. 1 | M78: article | N78: en | O78: =IF(F78="","",LOWER(TRIM(F78)&"|"&TRIM(G78)&"|"&H78)) | P78: No | Q78: Citations: 152
A79: A0078 | B79: Database | C79: OpenAlex | D79: 46287 | E79: Multiple queries (Q1-Q10) | F79: The impact of generative artificial intelligence on socioeconomic inequalities and policy making | G79: Valerio Capraro; Austin Lentsch; Daron Acemoğlu; Selin Akgün; Aisel Akhmedova; Ennio Bilancini; Jean‐François Bonnefon; Pablo Brañas‐Garza; Luigi Butera; Karen M. Douglas; Jim A. C. Everett; Gerd Gigerenzer; Christine Greenhow; Daniel A. Hashimoto; Julianne Holt‐Lunstad; Jolanda Jetten; Simon Johnson; Werner H. Kunz; Chiara Longoni; Pete Lunn; Simone Natale; Stefanie Paluch; Iyad Rahwan; Neil Selwyn; Vivek Singh; Siddharth Suri; Jennifer Sutcliffe; Joe Tomlinson; Sander van der Linden; Paul A. M. Van Lange; Friederike Wall; Jay Joseph Van Bavel; Riccardo Viale | H79: 2024 | I79: PNAS Nexus | J79: 10.1093/pnasnexus/pgae191 | K79: https://doi.org/10.1093/pnasnexus/pgae191 | L79: Abstract Generative artificial intelligence (AI) has the potential to both exacerbate and ameliorate existing socioeconomic inequalities. In this article, we provide a state-of-the-art interdisciplinary overview of the potential impacts of generative AI on (mis)information and three information-intensive domains: work, education, and healthcare. Our goal is to highlight how generative AI could worsen existing inequalities while illuminating how AI may help mitigate pervasive social problems. In the information domain, generative AI can democratize content creation and access but may dramatically expand the production and proliferation of misinformation. In the workplace, it can boost productivity and create new jobs, but the benefits will likely be distributed unevenly. In education, it offers personalized learning, but may widen the digital divide. In healthcare, it might improve diagnostics and accessibility, but could deepen pre-existing inequalities. In each section, we cover a specific topic, evaluate existing research, identify critical gaps, and recommend research directions, including explicit trade-offs that complicate the derivation of a priori hypotheses. We conclude with a section highlighting the role of policymaking to maximize generative AI's potential to reduce inequalities while mitigating its harmful effects. We discuss strengths and weaknesses of existing policy frameworks in the European Union, the United States, and the United Kingdom, observing that each fails to fully confront the socioeconomic challenges we have identified. We propose several concrete policies that could promote shared prosperity through the advancement of generative AI. This article emphasizes the need for interdisciplinary collaborations to understand and address the complex challenges of generative AI. | M79: article | N79: en | O79: =IF(F79="","",LOWER(TRIM(F79)&"|"&TRIM(G79)&"|"&H79)) | P79: No | Q79: Citations: 350
... A89: A0088 | B89: Database | C89: OpenAlex | D89: 46287 | E89: Multiple queries (Q1-Q10) | F89: Dynamic Graph CNN for Learning on Point Clouds | G89: Yue Wang; Yongbin Sun; Ziwei Liu; Sanjay E. Sarma; Michael M. Bronstein; Justin Solomon | H89: 2019 | I89: ACM Transactions on Graphics | J89: 10.1145/3326362 | K89: https://doi.org/10.1145/3326362 | L89: Point clouds provide a flexible geometric representation suitable for countless applications in computer graphics; they also comprise the raw output of most 3D data acquisition devices. While hand-designed features on point clouds have long been proposed in graphics and vision, however, the recent overwhelming success of convolutional neural networks (CNNs) for image analysis suggests the value of adapting insight from CNN to the point cloud world. Point clouds inherently lack topological information, so designing a model to recover topology can enrich the representation power of point clouds. To this end, we propose a new neural network module dubbed EdgeConv suitable for CNN-based high-level tasks on point clouds, including classification and segmentation. EdgeConv acts on graphs dynamically computed in each layer of the network. It is differentiable and can be plugged into existing architectures. Compared to existing modules operating in extrinsic space or treating each point independently, EdgeConv has several appealing properties: It incorporates local neighborhood information; it can be stacked applied to learn global shape properties; and in multi-layer systems affinity in feature space captures semantic characteristics over potentially long distances in the original embedding. We show the performance of our model on standard benchmarks, including ModelNet40, ShapeNetPart, and S3DIS. | M89: article | N89: en | O89: =IF(F89="","",LOWER(TRIM(F89)&"|"&TRIM(G89)&"|"&H89)) | P89: No | Q89: Citations: 7055
A90: A0089 | B90: Database | C90: OpenAlex | D90: 46287 | E90: Multiple queries (Q1-Q10) | F90: DiffTAD: Denoising diffusion probabilistic models for vehicle trajectory anomaly detection | G90: Chaoneng Li; Guanwen Feng; Yunan Li; Ruyi Liu; Qiguang Miao; Liang Chang | H90: 2024 | I90: Knowledge-Based Systems | J90: 10.1016/j.knosys.2024.111387 | K90: https://doi.org/10.1016/j.knosys.2024.111387 | M90: article | N90: en | O90: =IF(F90="","",LOWER(TRIM(F90)&"|"&TRIM(G90)&"|"&H90)) | P90: No | Q90: Citations: 51
A91: A0090 | B91: Database | C91: OpenAlex | D91: 46287 | E91: Multiple queries (Q1-Q10) | F91: Listen, Denoise, Action! Audio-Driven Motion Synthesis with Diffusion Models | G91: Simon Alexanderson; Rajmund Nagy; Jonas Beskow; Gustav Eje Henter | H91: 2023 | I91: ACM Transactions on Graphics | J91: 10.1145/3592458 | K91: https://doi.org/10.1145/3592458 | L91: Diffusion models have experienced a surge of interest as highly expressive yet efficiently trainable probabilistic models. We show that these models are an excellent fit for synthesising human motion that co-occurs with audio, e.g., dancing and co-speech gesticulation, since motion is complex and highly ambiguous given audio, calling for a probabilistic description. Specifically, we adapt the DiffWave architecture to model 3D pose sequences, putting Conformers in place of dilated convolutions for improved modelling power. We also demonstrate control over motion style, using classifier-free guidance to adjust the strength of the stylistic expression. Experiments on gesture and dance generation confirm that the proposed method achieves top-of-the-line motion quality, with distinctive styles whose expression can be made more or less pronounced. We also synthesise path-driven locomotion using the same model architecture. Finally, we generalise the guidance procedure to obtain product-of-expert ensembles of diffusion models and demonstrate how these may be used for, e.g., style interpolation, a contribution we believe is of independent interest. | M91: article | N91: en | O91: =IF(F91="","",LOWER(TRIM(F91)&"|"&TRIM(G91)&"|"&H91)) | P91: No | Q91: Citations: 189
A92: A0091 | B92: Database | C92: OpenAlex | D92: 46287 | E92: Multiple queries (Q1-Q10) | F92: Opportunities and Challenges of Generative AI in Construction Industry: Focusing on Adoption of Text-Based Models | G92: Prashnna Ghimire; Kyungki Kim; Manoj Acharya | H92: 2024 | I92: Buildings | J92: 10.3390/buildings14010220 | K92: https://doi.org/10.3390/buildings14010220 | L92: In the last decade, despite rapid advancements in artificial intelligence (AI) transforming many industry practices, construction largely lags in adoption. Recently, the emergence and rapid adoption of advanced large language models (LLMs) like OpenAI’s GPT, Google’s PaLM, and Meta’s Llama have shown great potential and sparked considerable global interest. However, the current surge lacks a study investigating the opportunities and challenges of implementing Generative AI (GenAI) in the construction sector, creating a critical knowledge gap for researchers and practitioners. This underlines the necessity to explore the prospects and complexities of GenAI integration. Bridging this gap is fundamental to optimizing GenAI’s early stage adoption within the construction sector. Given GenAI’s unprecedented capabilities to generate human-like content based on learning from existing content, we reflect on two guiding questions: What will the future bring for GenAI in the construction industry? What are the potential opportunities and challenges in implementing GenAI in the construction industry? This study delves into reflected perception in literature, analyzes the industry perception using programming-based word cloud and frequency analysis, and integrates authors’ opinions to answer these questions. This paper recommends a conceptual GenAI implementation framework, provides practical recommendations, summarizes future research questions, and builds foundational literature to foster subsequent research expansion in GenAI within the construction and its allied architecture and engineering domains. | M92: article | N92: en | O92: =IF(F92="","",LOWER(TRIM(F92)&"|"&TRIM(G92)&"|"&H92)) | P92: No | Q92: Citations: 154
A93: A0092 | B93: Database | C93: OpenAlex | D93: 46287 | E93: Multiple queries (Q1-Q10) | F93: Enhancing Work Productivity through Generative Artificial Intelligence: A Comprehensive Literature Review | G93: Humaid Al Naqbi; Zied Bahroun; Vian Ahmed | H93: 2024 | I93: Sustainability | J93: 10.3390/su16031166 | K93: https://doi.org/10.3390/su16031166 | L93: In this review, utilizing the PRISMA methodology, a comprehensive analysis of the use of Generative Artificial Intelligence (GAI) across diverse professional sectors is presented, drawing from 159 selected research publications. This study provides an insightful overview of the impact of GAI on enhancing institutional performance and work productivity, with a specific focus on sectors including academia, research, technology, communications, agriculture, government, and business. It highlights the critical role of GAI in navigating AI challenges, ethical considerations, and the importance of analytical thinking in these domains. The research conducts a detailed content analysis, uncovering significant trends and gaps in current GAI applications and projecting future prospects. A key aspect of this study is the bibliometric analysis, which identifies dominant tools like Chatbots and Conversational Agents, notably ChatGPT, as central to GAI’s evolution. The findings indicate a robust and accelerating trend in GAI research, expected to continue through 2024 and beyond. Additionally, this study points to potential future research directions, emphasizing the need for improved GAI design and strategic long-term planning, particularly in assessing its impact on user experience across various professional fields. | M93: article | N93: en | O93: =IF(F93="","",LOWER(TRIM(F93)&"|"&TRIM(G93)&"|"&H93)) | P93: No | Q93: Citations: 291
A94: A0093 | B94: Database | C94: OpenAlex | D94: 46287 | E94: Multiple queries (Q1-Q10) | F94: Revolutionizing Digital Pathology With the Power of Generative Artificial Intelligence and Foundation Models | G94: Asim Waqas; Marilyn M. Bui; Eric F. Glassy; Issam El Naqa; P Borkowski; Andrew Borkowski; Ghulam Rasool | H94: 2023 | I94: Laboratory Investigation | J94: 10.1016/j.labinv.2023.100255 | K94: https://doi.org/10.1016/j.labinv.2023.100255 | L94: Digital pathology has transformed the traditional pathology practice of analyzing tissue under a microscope into a computer vision workflow. Whole-slide imaging allows pathologists to view and analyze microscopic images on a computer monitor, enabling computational pathology. By leveraging artificial intelligence (AI) and machine learning (ML), computational pathology has emerged as a promising field in recent years. Recently, task-specific AI/ML (eg, convolutional neural networks) has risen to the forefront, achieving above-human performance in many image-processing and computer vision tasks. The performance of task-specific AI/ML models depends on the availability of many annotated training datasets, which presents a rate-limiting factor for AI/ML development in pathology. Task-specific AI/ML models cannot benefit from multimodal data and lack generalization, eg, the AI models often struggle to generalize to new datasets or unseen variations in image acquisition, staining techniques, or tissue types. The 2020s are witnessing the rise of foundation models and generative AI. A foundation model is a large AI model trained using sizable data, which is later adapted (or fine-tuned) to perform different tasks using a modest amount of task-specific annotated data. These AI models provide in-context learning, can self-correct mistakes, and promptly adjust to user feedback. In this review, we provide a brief overview of recent advances in computational pathology enabled by task-specific AI, their challenges and limitations, and then introduce various foundation models. We propose to create a pathology-specific generative AI based on multimodal foundation models and present its potentially transformative role in digital pathology. We describe different use cases, delineating how it could serve as an expert companion of pathologists and help them efficiently and objectively perform routine laboratory tasks, including quantifying image analysis, generating pathology reports, diagnosis, and prognosis. We also outline the potential role that foundation models and generative AI can play in standardizing the pathology laboratory workflow, education, and training. | M94: article | N94: en | O94: =IF(F94="","",LOWER(TRIM(F94)&"|"&TRIM(G94)&"|"&H94)) | P94: No | Q94: Citations: 136
A95: A0094 | B95: Database | C95: OpenAlex | D95: 46287 | E95: Multiple queries (Q1-Q10) | F95: A survey on deep learning applied to medical images: from simple artificial neural networks to generative models | G95: Pedro Celard; Eva Iglesias; José Manuel Sorribes-Fdez; R. Romero; Adrián Seara Vieira; L. Borrajo | H95: 2022 | I95: Neural Computing and Applications | J95: 10.1007/s00521-022-07953-4 | K95: https://doi.org/10.1007/s00521-022-07953-4 | M95: article | N95: en | O95: =IF(F95="","",LOWER(TRIM(F95)&"|"&TRIM(G95)&"|"&H95)) | P95: No | Q95: Citations: 182
A96: A0095 | B96: Database | C96: OpenAlex | D96: 46287 | E96: Multiple queries (Q1-Q10) | F96: Modelling Generative AI Acceptance, Perceived Teachers' Enthusiasm and Self‐Efficacy to English as a Foreign Language Learners' Well‐Being in the Digital Era | G96: Fangwei Huang; Yongliang Wang; Haijing Zhang | H96: 2024 | I96: European Journal of Education | J96: 10.1111/ejed.12770 | K96: https://doi.org/10.1111/ejed.12770 | L96: ABSTRACT As artificial intelligence (AI) has been integrated into foreign language (FL) education, learners' well‐being is influenced by various factors, including technological, personal and contextual elements. However, few studies explored how external and internal factors jointly shape FL learners' well‐being in the era of generative AI. To fill this gap, this study explores the effects of generative AI acceptance, perceived teachers' enthusiasm and self‐efficacy on FL learners' well‐being by investigating 613 university learners of English as a foreign language (EFL). The structural equation modelling results reveal that (1) generative AI acceptance positively predicts EFL learners' well‐being and self‐efficacy; (2) perceived teachers' enthusiasm does not predict learners' well‐being and positively predicts EFL learners' self‐efficacy; and (3) the self‐efficacy for receptive skills mediates the relationship between generative AI acceptance/perceived teachers' enthusiasm and EFL learners' well‐being, whereas self‐efficacy for productive skills does not play the mediation role. This research broadens the understanding of the antecedents of EFL learners' well‐being and extends the application of self‐efficacy theory in the AI‐driven educational environment, providing significant pedagogical implications. | M96: article | N96: en | O96: =IF(F96="","",LOWER(TRIM(F96)&"|"&TRIM(G96)&"|"&H96)) | P96: No | Q96: Citations: 231
A97: A0096 | B97: Database | C97: OpenAlex | D97: 46287 | E97: Multiple queries (Q1-Q10) | F97: The evolving field of digital mental health: current evidence and implementation issues for smartphone apps, generative artificial intelligence, and virtual reality | G97: John Torous; Jake Linardon; Simon B. Goldberg; Shufang Sun; Imogen Bell; Jennifer Nicholas; Lamiece Hassan; Yining Hua; Alyssa Milton; Joseph Firth | H97: 2025 | I97: World Psychiatry | J97: 10.1002/wps.21299 | K97: https://doi.org/10.1002/wps.21299 | L97: The expanding domain of digital mental health is transitioning beyond traditional telehealth to incorporate smartphone apps, virtual reality, and generative artificial intelligence, including large language models. While industry setbacks and methodological critiques have highlighted gaps in evidence and challenges in scaling these technologies, emerging solutions rooted in co-design, rigorous evaluation, and implementation science offer promising pathways forward. This paper underscores the dual necessity of advancing the scientific foundations of digital mental health and increasing its real-world applicability through five themes. First, we discuss recent technological advances in digital phenotyping, virtual reality, and generative artificial intelligence. Progress in this latter area, specifically designed to create new outputs such as conversations and images, holds unique potential for the mental health field. Given the spread of smartphone apps, we then evaluate the evidence supporting their utility across various mental health contexts, including well-being, depression, anxiety, schizophrenia, eating disorders, and substance use disorders. This broad view of the field highlights the need for a new generation of more rigorous, placebo-controlled, and real-world studies. We subsequently explore engagement challenges that hamper all digital mental health tools, and propose solutions, including human support, digital navigators, just-in-time adaptive interventions, and personalized approaches. We then analyze implementation issues, emphasizing clinician engagement, service integration, and scalable delivery models. We finally consider the need to ensure that innovations work for all people and thus can bridge digital health disparities, reviewing the evidence on tailoring digital tools for historically marginalized populations and lowand middle-income countries. Regarding digital mental health innovations as tools to augment and extend care, we conclude that smartphone apps, virtual reality, and large language models can positively impact mental health care if deployed correctly. | M97: article | N97: en | O97: =IF(F97="","",LOWER(TRIM(F97)&"|"&TRIM(G97)&"|"&H97)) | P97: No | Q97: Citations: 292
A98: A0097 | B98: Database | C98: OpenAlex | D98: 46287 | E98: Multiple queries (Q1-Q10) | F98: The Generative Adversarial Brain | G98: Samuel J. Gershman | H98: 2019 | I98: Frontiers in Artificial Intelligence | J98: 10.3389/frai.2019.00018 | K98: https://doi.org/10.3389/frai.2019.00018 | L98: The idea that the brain learns generative models of the world has been widely promulgated. Most approaches have assumed that the brain learns an explicit density model that assigns a probability to each possible state of the world. However, explicit density models are difficult to learn, requiring approximate inference techniques that may find poor solutions. An alternative approach is to learn an implicit density model that can sample from the generative model without evaluating the probabilities of those samples. The implicit model can be trained to fool a discriminator into believing that the samples are real. This is the idea behind generative adversarial algorithms, which have proven adept at learning realistic generative models. This paper develops an adversarial framework for probabilistic computation in the brain. It first considers how generative adversarial algorithms overcome some of the problems that vex prior theories based on explicit density models. It then discusses the psychological and neural evidence for this framework, as well as how the breakdown of the generator and discriminator could lead to delusions observed in some mental disorders. | M98: article | N98: en | O98: =IF(F98="","",LOWER(TRIM(F98)&"|"&TRIM(G98)&"|"&H98)) | P98: No | Q98: Citations: 98
A99: A0098 | B99: Database | C99: OpenAlex | D99: 46287 | E99: Multiple queries (Q1-Q10) | F99: Deepfake video detection: challenges and opportunities | G99: Achhardeep Kaur; Azadeh Noori Hoshyar; Vidya Saikrishna; Sally Firmin; Feng Xia | H99: 2024 | I99: Artificial Intelligence Review | J99: 10.1007/s10462-024-10810-6 | K99: https://doi.org/10.1007/s10462-024-10810-6 | L99: Abstract Deepfake videos are a growing social issue. These videos are manipulated by artificial intelligence (AI) techniques (especially deep learning), an emerging societal issue. Malicious individuals misuse deepfake technologies to spread false information, such as fake images, videos, and audio. The development of convincing fake content threatens politics, security, and privacy. The majority of deepfake video detection methods are data-driven. This survey paper aims to thoroughly analyse deepfake video generation and detection. The paper’s main contribution is the classification of the many challenges encountered while detecting deepfake videos. The paper discusses data challenges such as unbalanced datasets and inadequate labelled training data. Training challenges include the need for many computational resources. It also addresses reliability challenges, including overconfidence in detection methods and emerging manipulation approaches. The research emphasises the dominance of deep learning-based methods in detecting deepfakes despite their computational efficiency and generalisation limitations. However, it also acknowledges the drawbacks of these approaches, such as their limited computing efficiency and generalisation. The research also critically evaluates deepfake datasets, emphasising the necessity for good-quality datasets to improve detection methods. The study also indicates major research gaps, guiding future deepfake detection research. This entails developing robust models for real-time detection. | M99: article | N99: en | O99: =IF(F99="","",LOWER(TRIM(F99)&"|"&TRIM(G99)&"|"&H99)) | P99: No | Q99: Citations: 198
A100: A0099 | B100: Database | C100: OpenAlex | D100: 46287 | E100: Multiple queries (Q1-Q10) | F100: Challenges for higher education in the era of widespread access to generative AI | G100: Krzysztof Walczak; Wojciech Cellary | H100: 2023 | I100: Economics and Business Review/The Poznań University of Economics Review | J100: 10.18559/ebr.2023.2.743 | K100: https://doi.org/10.18559/ebr.2023.2.743 | L100: The aim of this paper is to discuss the role and impact of generative artificial intelligence (AI) systems in higher education. The proliferation of AI models such as GPT-4, Open Assistant and DALL-E presents a paradigm shift in information acquisition and learning. This transformation poses substantial challenges for traditional teaching approaches and the role of educators. The paper explores the advantages and potential threats of using generative AI in education and necessary changes in curricula. It further discusses the need to foster digital literacy and the ethical use of AI. The paper’s findings are based on a survey conducted among university students exploring their usage and perception of these AI systems. Finally, recommendations for the use of AI in higher education are offered, which emphasize the need to harness AI's potential while mitigating its risks. This discourse aims at stimulating policy and strategy development to ensure relevant and effective education in the rapidly evolving digital landscape. | M100: article | N100: en | O100: =IF(F100="","",LOWER(TRIM(F100)&"|"&TRIM(G100)&"|"&H100)) | P100: No | Q100: Citations: 192
A101: A0100 | B101: Database | C101: OpenAlex | D101: 46287 | E101: Multiple queries (Q1-Q10) | F101: Generative Artificial Intelligence in Education: From Deceptive to Disruptive. | G101: Marc Alier; Francisco José García‐Peñalvo; Jorge D. Camba | H101: 2024 | I101: International Journal of Interactive Multimedia and Artificial Intelligence | J101: 10.9781/ijimai.2024.02.011 | K101: https://doi.org/10.9781/ijimai.2024.02.011 | L101: Generative Artificial Intelligence (GenAI) has emerged as a promising technology that can create original content, such as text, images, and sound. The use of GenAI in educational settings is becoming increasingly popular and offers a range of opportunities and challenges. This special issue explores the management and integration of GenAI in educational settings, including the ethical considerations, best practices, and opportunities. The potential of GenAI in education is vast. By using algorithms and data, GenAI can create original content that can be used to augment traditional teaching methods, creating a more interactive and personalized learning experience. In addition, GenAI can be utilized as an assessment tool and for providing feedback to students using generated content. For instance, it can be used to create custom quizzes, generate essay prompts, or even grade essays. The use of GenAI as an assessment tool can reduce the workload of teachers and help students receive prompt feedback on their work. Incorporating GenAI in educational settings also poses challenges related to academic integrity. With availability of GenAI models, students can use them to study or complete their homework assignments, which can raise concerns about the authenticity and authorship of the delivered work. Therefore, it is important to ensure that academic standards are maintained, and the originality of the student's work is preserved. This issue highlights the need for implementing ethical practices in the use of GenAI models and ensuring that the technology is used to support and not replace the student's learning experience. | M101: article | N101: en | O101: =IF(F101="","",LOWER(TRIM(F101)&"|"&TRIM(G101)&"|"&H101)) | P101: No | Q101: Citations: 169
A102: A0101 | B102: Database | C102: OpenAlex | D102: 46287 | E102: Multiple queries (Q1-Q10) | F102: Quantum‐Noise‐Driven Generative Diffusion Models | G102: Marco Parigi; Stefano Martina; Filippo Caruso | H102: 2024 | I102: Advanced Quantum Technologies | J102: 10.1002/qute.202300401 | K102: https://doi.org/10.1002/qute.202300401 | L102: Abstract Generative models realized with Machine Learning (ML) techniques are powerful tools to infer complex and unknown data distributions from a finite number of training samples in order to produce new synthetic data. Diffusion Models (DMs) are an emerging framework that have recently overcome Generative Adversarial Networks (GANs) in creating high‐quality images. Here, is proposed and discussed the quantum generalization of DMs, i.e., three Quantum‐Noise‐Driven Generative Diffusion Models (QNDGDMs) that could be experimentally tested on real quantum systems. The idea is to harness unique quantum features, in particular the non‐trivial interplay among coherence, entanglement, and noise that the currently available noisy quantum processors do unavoidably suffer from, in order to overcome the main computational burdens of classical diffusion models during inference. Hence, the suggestion is to exploit quantum noise not as an issue to be detected and solved but instead as a beneficial key ingredient to generate complex probability distributions from which a quantum processor might sample more efficiently than a classical one. Three examples of the numerical simulations are also included for the proposed approaches. The results are expected to pave the way for new quantum‐inspired or quantum‐based generative diffusion algorithms addressing tasks as data generation with widespread real‐world applications. | M102: article | N102: en | O102: =IF(F102="","",LOWER(TRIM(F102)&"|"&TRIM(G102)&"|"&H102)) | P102: No | Q102: Citations: 36
A103: A0102 | B103: Database | C103: OpenAlex | D103: 46287 | E103: Multiple queries (Q1-Q10) | F103: DPM-Solver++: Fast Solver for Guided Sampling of Diffusion Probabilistic Models | G103: Cheng Lu; Yuhao Zhou; Fan Bao; Jianfei Chen; Chongxuan Li; Jun Zhu | H103: 2025 | I103: Machine Intelligence Research | J103: 10.1007/s11633-025-1562-4 | K103: https://doi.org/10.1007/s11633-025-1562-4 | L103: Abstract Diffusion probabilistic models (DPMs) have achieved impressive success in high-resolution image synthesis, especially in recent large-scale text-to-image generation applications. An essential technique for improving the sample quality of DPMs is guided sampling, which usually needs a large guidance scale to obtain the best sample quality. The commonly-used fast sampler for guided sampling is denoising diffusion implicit models (DDIM), a first-order diffusion ordinary differential equation (ODE) solver that generally needs 100 to 250 steps for high-quality samples. Although recent works propose dedicated high-order solvers and achieve a further speedup for sampling without guidance, their effectiveness for guided sampling has not been well-tested before. In this work, we demonstrate that previous high-order fast samplers suffer from instability issues, and they even become slower than DDIM when the guidance scale grows larger. To further speed up guided sampling, we propose DPM-Solver++, a high-order solver for the guided sampling of DPMs. DPM-Solver++ solves the diffusion ODE with the data prediction model and adopts thresholding methods to keep the solution matches training data distribution. We further propose a multistep variant of DPM-Solver++ to address the instability issue by reducing the effective step size. Experiments show that DPM-Solver++ can generate high-quality samples within only 15 to 20 steps for guided sampling by pixel-space and latent-space DPMs. | M103: article | N103: en | O103: =IF(F103="","",LOWER(TRIM(F103)&"|"&TRIM(G103)&"|"&H103)) | P103: No | Q103: Citations: 143
A104: A0103 | B104: Database | C104: OpenAlex | D104: 46287 | E104: Multiple queries (Q1-Q10) | F104: What Do We Mean by GenAI? A Systematic Mapping of The Evolution, Trends, and Techniques Involved in Generative AI. | G104: Francisco José García‐Peñalvo; Andrea Vázquez‐Ingelmo | H104: 2023 | I104: International Journal of Interactive Multimedia and Artificial Intelligence | J104: 10.9781/ijimai.2023.07.006 | K104: https://doi.org/10.9781/ijimai.2023.07.006 | L104: Artificial Intelligence has become a focal point of interest across various sectors due to its ability to generate creative and realistic outputs. A specific subset, generative artificial intelligence, has seen significant growth, particularly in late 2022. Tools like ChatGPT, Dall-E, or Midjourney have democratized access to Large Language Models, enabling the creation of human-like content. However, the concept 'Generative Artificial Intelligence lacks a universally accepted definition, leading to potential misunderstandings. While a model that produces any output can be technically seen as generative, the Artificial Intelligent research community often reserves the term for complex models that generate high-quality, human-like material. This paper presents a literature mapping of AI-driven content generation, analyzing 631 solutions published over the last five years to better understand and characterize the Generative Artificial Intelligence landscape. Our findings suggest a dichotomy in the understanding and application of the term "Generative AI". While the broader public often interprets "Generative AI" as AI-driven creation of tangible content, the AI research community mainly discusses generative implementations with an emphasis on the models in use, without explicitly categorizing their work under the term "Generative AI". | M104: article | N104: en | O104: =IF(F104="","",LOWER(TRIM(F104)&"|"&TRIM(G104)&"|"&H104)) | P104: No | Q104: Citations: 234
A105: A0104 | B105: Database | C105: OpenAlex | D105: 46287 | E105: Multiple queries (Q1-Q10) | F105: A Survey of Generative AI Applications | G105: Roberto Gozalo-Brizuela; Eduardo Eduardo Garrido Merchan | H105: 2024 | I105: Journal of Computer Science | J105: 10.3844/jcssp.2024.801.818 | K105: https://doi.org/10.3844/jcssp.2024.801.818 | L105: Generative AI has experienced remarkable growth in recent years, leading to a wide array of applications across diverse domains. In this study, we present a comprehensive survey of more than 350 generative AI applications, providing a structured taxonomy and concise descriptions of various unimodal and even multimodal generative AIs. The survey is organized into sections, covering a wide range of unimodal generative AI applications such as text (ChatGPT or Bard), images (DALL-E 3 or Midjourney), video (Colossyan AI and Synthesia AI), gaming (CSM and ConvAI) and brain (Meta’s speech from brain) information. Our survey provides an updated outlook of the generative AGI landscape, giving several examples of each technology, something not achieved in a paper before to our knowledge. Other surveys have focused on reviewing the impact of generative on different industries while not diving deep into which technologies or models to use. A thorough web and industry analysis was conducted to get examples for each of the sections. Ethical considerations were followed for the composition of this study. | M105: article | N105: en | O105: =IF(F105="","",LOWER(TRIM(F105)&"|"&TRIM(G105)&"|"&H105)) | P105: No | Q105: Citations: 91
